{
  "demand": {
    "Steel Coils": {
      "forecasts": [
        362.9,
        282.4,
        222.5,
        145.5,
        80.8,
        74.3
      ],
      "hw_forecasts": [
        432.4,
        323.9,
        227.6,
        104.3,
        0,
        0
      ],
      "ar_forecasts": [
        258.6,
        220.1,
        214.9,
        207.4,
        202.0,
        185.8
      ],
      "ci_lower": [
        298.2,
        217.7,
        157.8,
        80.8,
        16.1,
        9.6
      ],
      "ci_upper": [
        467.5,
        406.8,
        327.1,
        269.9,
        205.2,
        178.9
      ],
      "trend": "Decreasing",
      "method": "Ensemble: Holt-Winters (60%) + AR(6) (40%)",
      "ar_order": 6,
      "ar_aic": 254.45,
      "hw_params": {
        "alpha": 0.7,
        "beta": 0.1,
        "gamma": 0.6
      },
      "history_dates": [
        "2023-04",
        "2023-05",
        "2023-06",
        "2023-07",
        "2023-08",
        "2023-09",
        "2023-10",
        "2023-11",
        "2023-12",
        "2024-01",
        "2024-02",
        "2024-03",
        "2024-04",
        "2024-05",
        "2024-06",
        "2024-07",
        "2024-08",
        "2024-09",
        "2024-10",
        "2024-11",
        "2024-12",
        "2025-01",
        "2025-02",
        "2025-03",
        "2025-04",
        "2025-05",
        "2025-06",
        "2025-07",
        "2025-08",
        "2025-09",
        "2025-10",
        "2025-11",
        "2025-12",
        "2026-01",
        "2026-02",
        "2026-03"
      ],
      "history_values": [
        732,
        771,
        647,
        559,
        422,
        211,
        205,
        174,
        117,
        180,
        157,
        46,
        38,
        65,
        20,
        20,
        146,
        192,
        132,
        20,
        81,
        20,
        48,
        24,
        171,
        108,
        145,
        143,
        216,
        298,
        287,
        250,
        324,
        281,
        263,
        252
      ]
    },
    "Aluminum Sheets": {
      "forecasts": [
        7.2,
        7.0,
        6.8,
        6.7,
        6.7,
        6.5
      ],
      "hw_forecasts": [
        0,
        0,
        0,
        0,
        0,
        0
      ],
      "ar_forecasts": [
        17.9,
        17.4,
        17.1,
        16.8,
        16.8,
        16.2
      ],
      "ci_lower": [
        0,
        0,
        0,
        0,
        0,
        0
      ],
      "ci_upper": [
        51.3,
        56.2,
        87.5,
        87.4,
        55.9,
        55.7
      ],
      "trend": "Decreasing",
      "method": "Ensemble: Holt-Winters (60%) + AR(6) (40%)",
      "ar_order": 6,
      "ar_aic": 198.07,
      "hw_params": {
        "alpha": 0.7,
        "beta": 0.15,
        "gamma": 0.1
      },
      "history_dates": [
        "2023-04",
        "2023-05",
        "2023-06",
        "2023-07",
        "2023-08",
        "2023-09",
        "2023-10",
        "2023-11",
        "2023-12",
        "2024-01",
        "2024-02",
        "2024-03",
        "2024-04",
        "2024-05",
        "2024-06",
        "2024-07",
        "2024-08",
        "2024-09",
        "2024-10",
        "2024-11",
        "2024-12",
        "2025-01",
        "2025-02",
        "2025-03",
        "2025-04",
        "2025-05",
        "2025-06",
        "2025-07",
        "2025-08",
        "2025-09",
        "2025-10",
        "2025-11",
        "2025-12",
        "2026-01",
        "2026-02",
        "2026-03"
      ],
      "history_values": [
        612,
        410,
        444,
        463,
        464,
        390,
        264,
        241,
        221,
        213,
        235,
        138,
        168,
        142,
        134,
        104,
        104,
        104,
        72,
        57,
        40,
        20,
        20,
        20,
        20,
        43,
        20,
        20,
        94,
        36,
        20,
        20,
        20,
        20,
        20,
        20
      ]
    },
    "Copper Wire": {
      "forecasts": [
        169.2,
        90.3,
        106.3,
        99.0,
        114.6,
        133.9
      ],
      "hw_forecasts": [
        144.0,
        33.6,
        32.2,
        0,
        0,
        0
      ],
      "ar_forecasts": [
        207.1,
        175.4,
        217.4,
        247.6,
        286.4,
        334.8
      ],
      "ci_lower": [
        142.7,
        44.4,
        79.7,
        53.1,
        88.0,
        107.3
      ],
      "ci_upper": [
        202.8,
        134.7,
        139.9,
        132.6,
        148.2,
        167.5
      ],
      "trend": "Decreasing",
      "method": "Ensemble: Holt-Winters (60%) + AR(6) (40%)",
      "ar_order": 6,
      "ar_aic": 253.17,
      "hw_params": {
        "alpha": 0.7,
        "beta": 0.15,
        "gamma": 0.1
      },
      "history_dates": [
        "2023-04",
        "2023-05",
        "2023-06",
        "2023-07",
        "2023-08",
        "2023-09",
        "2023-10",
        "2023-11",
        "2023-12",
        "2024-01",
        "2024-02",
        "2024-03",
        "2024-04",
        "2024-05",
        "2024-06",
        "2024-07",
        "2024-08",
        "2024-09",
        "2024-10",
        "2024-11",
        "2024-12",
        "2025-01",
        "2025-02",
        "2025-03",
        "2025-04",
        "2025-05",
        "2025-06",
        "2025-07",
        "2025-08",
        "2025-09",
        "2025-10",
        "2025-11",
        "2025-12",
        "2026-01",
        "2026-02",
        "2026-03"
      ],
      "history_values": [
        500,
        514,
        443,
        484,
        417,
        326,
        344,
        260,
        215,
        181,
        244,
        229,
        241,
        263,
        254,
        332,
        317,
        267,
        292,
        279,
        204,
        175,
        179,
        355,
        322,
        320,
        367,
        381,
        375,
        361,
        260,
        409,
        274,
        223,
        146,
        113
      ]
    },
    "Plastic Pellets": {
      "forecasts": [
        324.3,
        342.4,
        401.4,
        289.1,
        269.6,
        157.0
      ],
      "hw_forecasts": [
        337.0,
        316.0,
        398.6,
        222.3,
        183.6,
        0
      ],
      "ar_forecasts": [
        305.3,
        381.9,
        405.5,
        389.3,
        398.7,
        392.4
      ],
      "ci_lower": [
        276.5,
        294.6,
        353.6,
        241.3,
        221.8,
        109.2
      ],
      "ci_upper": [
        409.6,
        452.8,
        511.8,
        399.5,
        380.0,
        242.3
      ],
      "trend": "Increasing",
      "method": "Ensemble: Holt-Winters (60%) + AR(6) (40%)",
      "ar_order": 6,
      "ar_aic": 300.21,
      "hw_params": {
        "alpha": 0.7,
        "beta": 0.05,
        "gamma": 0.1
      },
      "history_dates": [
        "2023-04",
        "2023-05",
        "2023-06",
        "2023-07",
        "2023-08",
        "2023-09",
        "2023-10",
        "2023-11",
        "2023-12",
        "2024-01",
        "2024-02",
        "2024-03",
        "2024-04",
        "2024-05",
        "2024-06",
        "2024-07",
        "2024-08",
        "2024-09",
        "2024-10",
        "2024-11",
        "2024-12",
        "2025-01",
        "2025-02",
        "2025-03",
        "2025-04",
        "2025-05",
        "2025-06",
        "2025-07",
        "2025-08",
        "2025-09",
        "2025-10",
        "2025-11",
        "2025-12",
        "2026-01",
        "2026-02",
        "2026-03"
      ],
      "history_values": [
        1163,
        1262,
        1269,
        1379,
        1230,
        1212,
        1049,
        890,
        808,
        785,
        690,
        704,
        804,
        902,
        913,
        1056,
        968,
        1257,
        1052,
        954,
        729,
        690,
        678,
        479,
        455,
        520,
        258,
        457,
        462,
        284,
        136,
        155,
        76,
        54,
        208,
        273
      ]
    },
    "Carbon Fiber": {
      "forecasts": [
        30.4,
        8.6,
        8.6,
        8.7,
        8.6,
        8.6
      ],
      "hw_forecasts": [
        36.4,
        0,
        0,
        0,
        0,
        0
      ],
      "ar_forecasts": [
        21.4,
        21.5,
        21.6,
        21.7,
        21.6,
        21.5
      ],
      "ci_lower": [
        13.9,
        0,
        0,
        0,
        0,
        0
      ],
      "ci_upper": [
        45.6,
        31.6,
        31.6,
        31.7,
        31.6,
        23.8
      ],
      "trend": "Decreasing",
      "method": "Ensemble: Holt-Winters (60%) + AR(6) (40%)",
      "ar_order": 6,
      "ar_aic": 80.97,
      "hw_params": {
        "alpha": 0.7,
        "beta": 0.1,
        "gamma": 0.6
      },
      "history_dates": [
        "2023-04",
        "2023-05",
        "2023-06",
        "2023-07",
        "2023-08",
        "2023-09",
        "2023-10",
        "2023-11",
        "2023-12",
        "2024-01",
        "2024-02",
        "2024-03",
        "2024-04",
        "2024-05",
        "2024-06",
        "2024-07",
        "2024-08",
        "2024-09",
        "2024-10",
        "2024-11",
        "2024-12",
        "2025-01",
        "2025-02",
        "2025-03",
        "2025-04",
        "2025-05",
        "2025-06",
        "2025-07",
        "2025-08",
        "2025-09",
        "2025-10",
        "2025-11",
        "2025-12",
        "2026-01",
        "2026-02",
        "2026-03"
      ],
      "history_values": [
        158,
        140,
        93,
        91,
        59,
        43,
        28,
        22,
        20,
        27,
        20,
        27,
        20,
        23,
        20,
        20,
        21,
        20,
        20,
        20,
        21,
        20,
        20,
        29,
        20,
        20,
        31,
        27,
        24,
        20,
        20,
        20,
        20,
        20,
        20,
        20
      ]
    },
    "Silicon Wafers": {
      "forecasts": [
        82.1,
        138.1,
        88.1,
        64.1,
        30.1,
        29.2
      ],
      "hw_forecasts": [
        80.5,
        175.1,
        92.3,
        54.6,
        0,
        0
      ],
      "ar_forecasts": [
        84.5,
        82.6,
        81.9,
        78.4,
        75.3,
        72.9
      ],
      "ci_lower": [
        62.2,
        118.2,
        51.4,
        44.2,
        10.2,
        0
      ],
      "ci_upper": [
        140.5,
        196.5,
        136.1,
        122.5,
        78.1,
        87.6
      ],
      "trend": "Increasing",
      "method": "Ensemble: Holt-Winters (60%) + AR(6) (40%)",
      "ar_order": 6,
      "ar_aic": 198.54,
      "hw_params": {
        "alpha": 0.7,
        "beta": 0.05,
        "gamma": 0.1
      },
      "history_dates": [
        "2023-04",
        "2023-05",
        "2023-06",
        "2023-07",
        "2023-08",
        "2023-09",
        "2023-10",
        "2023-11",
        "2023-12",
        "2024-01",
        "2024-02",
        "2024-03",
        "2024-04",
        "2024-05",
        "2024-06",
        "2024-07",
        "2024-08",
        "2024-09",
        "2024-10",
        "2024-11",
        "2024-12",
        "2025-01",
        "2025-02",
        "2025-03",
        "2025-04",
        "2025-05",
        "2025-06",
        "2025-07",
        "2025-08",
        "2025-09",
        "2025-10",
        "2025-11",
        "2025-12",
        "2026-01",
        "2026-02",
        "2026-03"
      ],
      "history_values": [
        283,
        261,
        365,
        284,
        252,
        122,
        87,
        58,
        57,
        20,
        43,
        60,
        74,
        62,
        55,
        46,
        67,
        82,
        154,
        111,
        117,
        109,
        97,
        76,
        61,
        67,
        39,
        68,
        109,
        65,
        47,
        24,
        26,
        29,
        62,
        80
      ]
    },
    "Titanium Alloy": {
      "forecasts": [
        24.3,
        19.9,
        16.3,
        9.6,
        9.1,
        10.0
      ],
      "hw_forecasts": [
        26.7,
        20.4,
        14.1,
        2.2,
        0,
        0
      ],
      "ar_forecasts": [
        20.8,
        19.1,
        19.6,
        20.7,
        22.7,
        25.1
      ],
      "ci_lower": [
        13.8,
        15.2,
        5.8,
        0,
        0,
        0
      ],
      "ci_upper": [
        32.2,
        29.6,
        24.2,
        17.5,
        17.0,
        17.9
      ],
      "trend": "Decreasing",
      "method": "Ensemble: Holt-Winters (60%) + AR(6) (40%)",
      "ar_order": 6,
      "ar_aic": 112.92,
      "hw_params": {
        "alpha": 0.7,
        "beta": 0.1,
        "gamma": 0.1
      },
      "history_dates": [
        "2023-04",
        "2023-05",
        "2023-06",
        "2023-07",
        "2023-08",
        "2023-09",
        "2023-10",
        "2023-11",
        "2023-12",
        "2024-01",
        "2024-02",
        "2024-03",
        "2024-04",
        "2024-05",
        "2024-06",
        "2024-07",
        "2024-08",
        "2024-09",
        "2024-10",
        "2024-11",
        "2024-12",
        "2025-01",
        "2025-02",
        "2025-03",
        "2025-04",
        "2025-05",
        "2025-06",
        "2025-07",
        "2025-08",
        "2025-09",
        "2025-10",
        "2025-11",
        "2025-12",
        "2026-01",
        "2026-02",
        "2026-03"
      ],
      "history_values": [
        91,
        84,
        82,
        80,
        72,
        54,
        41,
        20,
        20,
        20,
        20,
        20,
        20,
        21,
        20,
        20,
        27,
        21,
        20,
        20,
        20,
        20,
        22,
        26,
        24,
        35,
        39,
        52,
        53,
        50,
        44,
        53,
        47,
        36,
        30,
        22
      ]
    },
    "Nickel Powder": {
      "forecasts": [
        52.4,
        37.5,
        26.9,
        20.6,
        10.2,
        9.9
      ],
      "hw_forecasts": [
        69.5,
        44.5,
        27.1,
        17.2,
        0,
        0
      ],
      "ar_forecasts": [
        26.7,
        26.9,
        26.6,
        25.7,
        25.4,
        24.7
      ],
      "ci_lower": [
        46.9,
        32.0,
        0,
        15.1,
        4.7,
        0
      ],
      "ci_upper": [
        79.0,
        63.0,
        53.5,
        47.2,
        35.7,
        35.4
      ],
      "trend": "Increasing",
      "method": "Ensemble: Holt-Winters (60%) + AR(6) (40%)",
      "ar_order": 6,
      "ar_aic": 149.8,
      "hw_params": {
        "alpha": 0.7,
        "beta": 0.15,
        "gamma": 0.1
      },
      "history_dates": [
        "2023-04",
        "2023-05",
        "2023-06",
        "2023-07",
        "2023-08",
        "2023-09",
        "2023-10",
        "2023-11",
        "2023-12",
        "2024-01",
        "2024-02",
        "2024-03",
        "2024-04",
        "2024-05",
        "2024-06",
        "2024-07",
        "2024-08",
        "2024-09",
        "2024-10",
        "2024-11",
        "2024-12",
        "2025-01",
        "2025-02",
        "2025-03",
        "2025-04",
        "2025-05",
        "2025-06",
        "2025-07",
        "2025-08",
        "2025-09",
        "2025-10",
        "2025-11",
        "2025-12",
        "2026-01",
        "2026-02",
        "2026-03"
      ],
      "history_values": [
        225,
        261,
        240,
        228,
        224,
        200,
        189,
        177,
        143,
        99,
        108,
        74,
        71,
        71,
        58,
        40,
        20,
        20,
        20,
        20,
        20,
        20,
        20,
        20,
        20,
        20,
        33,
        32,
        37,
        31,
        20,
        20,
        20,
        20,
        24,
        28
      ]
    },
    "Graphite Electrodes": {
      "forecasts": [
        49.2,
        20.0,
        12.3,
        12.0,
        12.4,
        12.8
      ],
      "hw_forecasts": [
        64.1,
        12.6,
        0,
        0,
        0,
        0
      ],
      "ar_forecasts": [
        26.8,
        31.1,
        30.8,
        29.9,
        31.1,
        32.0
      ],
      "ci_lower": [
        21.1,
        0,
        0,
        0,
        0,
        0
      ],
      "ci_upper": [
        85.4,
        64.0,
        56.3,
        56.0,
        56.4,
        49.0
      ],
      "trend": "Decreasing",
      "method": "Ensemble: Holt-Winters (60%) + AR(6) (40%)",
      "ar_order": 6,
      "ar_aic": 147.05,
      "hw_params": {
        "alpha": 0.7,
        "beta": 0.1,
        "gamma": 0.4
      },
      "history_dates": [
        "2023-04",
        "2023-05",
        "2023-06",
        "2023-07",
        "2023-08",
        "2023-09",
        "2023-10",
        "2023-11",
        "2023-12",
        "2024-01",
        "2024-02",
        "2024-03",
        "2024-04",
        "2024-05",
        "2024-06",
        "2024-07",
        "2024-08",
        "2024-09",
        "2024-10",
        "2024-11",
        "2024-12",
        "2025-01",
        "2025-02",
        "2025-03",
        "2025-04",
        "2025-05",
        "2025-06",
        "2025-07",
        "2025-08",
        "2025-09",
        "2025-10",
        "2025-11",
        "2025-12",
        "2026-01",
        "2026-02",
        "2026-03"
      ],
      "history_values": [
        334,
        327,
        278,
        234,
        188,
        199,
        128,
        81,
        55,
        52,
        65,
        44,
        20,
        20,
        20,
        24,
        20,
        36,
        22,
        20,
        29,
        32,
        47,
        50,
        66,
        43,
        34,
        32,
        38,
        54,
        28,
        20,
        27,
        24,
        20,
        24
      ]
    },
    "Rare Earth Magnets": {
      "forecasts": [
        21.8,
        20.2,
        18.0,
        11.5,
        8.4,
        8.4
      ],
      "hw_forecasts": [
        22.4,
        19.8,
        16.1,
        5.2,
        0,
        0
      ],
      "ar_forecasts": [
        20.8,
        20.8,
        20.8,
        20.9,
        20.9,
        20.9
      ],
      "ci_lower": [
        17.3,
        14.7,
        14.4,
        7.0,
        2.9,
        3.9
      ],
      "ci_upper": [
        26.7,
        25.1,
        22.9,
        16.4,
        14.0,
        13.3
      ],
      "trend": "Decreasing",
      "method": "Ensemble: Holt-Winters (60%) + AR(6) (40%)",
      "ar_order": 6,
      "ar_aic": 61.05,
      "hw_params": {
        "alpha": 0.7,
        "beta": 0.1,
        "gamma": 0.4
      },
      "history_dates": [
        "2023-04",
        "2023-05",
        "2023-06",
        "2023-07",
        "2023-08",
        "2023-09",
        "2023-10",
        "2023-11",
        "2023-12",
        "2024-01",
        "2024-02",
        "2024-03",
        "2024-04",
        "2024-05",
        "2024-06",
        "2024-07",
        "2024-08",
        "2024-09",
        "2024-10",
        "2024-11",
        "2024-12",
        "2025-01",
        "2025-02",
        "2025-03",
        "2025-04",
        "2025-05",
        "2025-06",
        "2025-07",
        "2025-08",
        "2025-09",
        "2025-10",
        "2025-11",
        "2025-12",
        "2026-01",
        "2026-02",
        "2026-03"
      ],
      "history_values": [
        59,
        54,
        53,
        51,
        41,
        31,
        20,
        20,
        20,
        20,
        20,
        20,
        20,
        20,
        20,
        20,
        20,
        20,
        20,
        20,
        20,
        20,
        20,
        22,
        20,
        32,
        22,
        20,
        24,
        20,
        20,
        20,
        20,
        20,
        20,
        20
      ]
    }
  },
  "prices": {
    "Steel Coils": {
      "predictions": [
        800.25,
        778.33,
        782.31,
        840.39,
        801.25,
        807.54
      ],
      "arima_predictions": [
        807.06,
        826.45,
        762.91,
        830.65,
        788.9,
        792.15
      ],
      "gb_predictions": [
        791.92,
        719.51,
        806.02,
        852.29,
        816.34,
        826.34
      ],
      "ci_lower": [
        647.34,
        562.09,
        517.47,
        534.58,
        459.34,
        433.0
      ],
      "ci_upper": [
        953.16,
        994.57,
        1047.15,
        1146.2,
        1143.16,
        1182.08
      ],
      "current_price": 751.2,
      "ema_values": [
        856.66,
        828.4114,
        818.0082,
        834.6515,
        835.8968,
        824.6777,
        821.9841,
        848.2029,
        872.5421,
        892.6043,
        894.646,
        887.6014,
        948.7867,
        947.7991,
        945.4565,
        917.3003,
        874.1688,
        811.8777,
        726.4955,
        684.8225,
        700.5761,
        691.7858,
        749.087,
        784.0878,
        793.257,
        801.9036,
        829.4683,
        796.5316,
        796.2169,
        797.7063,
        794.9245,
        888.9318,
        889.3599,
        877.5656,
        888.424,
        849.2172
      ],
      "volatility_pct": 13.57,
      "rsi": 52.7,
      "macd_line": 8.9996,
      "macd_signal": 4.2752,
      "macd_histogram": 4.7244,
      "bb_upper": 1051.52,
      "bb_mid": 792.81,
      "bb_lower": 534.1,
      "price_signal": "BUY NOW",
      "signal_reason": "Price projected to rise 6.7% | MACD bullish crossover",
      "signal_color": "red",
      "pct_change_expected": 6.72,
      "method": "Ensemble: ARIMA(3,1,2) + Gradient Boosted Trees",
      "history_dates": [
        "2023-04",
        "2023-05",
        "2023-06",
        "2023-07",
        "2023-08",
        "2023-09",
        "2023-10",
        "2023-11",
        "2023-12",
        "2024-01",
        "2024-02",
        "2024-03",
        "2024-04",
        "2024-05",
        "2024-06",
        "2024-07",
        "2024-08",
        "2024-09",
        "2024-10",
        "2024-11",
        "2024-12",
        "2025-01",
        "2025-02",
        "2025-03",
        "2025-04",
        "2025-05",
        "2025-06",
        "2025-07",
        "2025-08",
        "2025-09",
        "2025-10",
        "2025-11",
        "2025-12",
        "2026-01",
        "2026-02",
        "2026-03"
      ],
      "history_values": [
        856.66,
        757.79,
        792.0,
        876.26,
        839.01,
        796.63,
        815.25,
        913.75,
        933.39,
        942.76,
        899.75,
        869.99,
        1101.75,
        945.33,
        939.6,
        846.91,
        766.34,
        656.15,
        513.04,
        580.64,
        739.96,
        669.81,
        892.34,
        871.59,
        816.18,
        823.52,
        898.38,
        714.19,
        795.43,
        801.43,
        787.97,
        1123.95,
        890.43,
        848.08,
        915.57,
        751.2
      ]
    },
    "Aluminum Sheets": {
      "predictions": [
        3012.61,
        2918.71,
        2832.94,
        2863.13,
        2884.18,
        3084.98
      ],
      "arima_predictions": [
        3019.75,
        3052.0,
        2991.04,
        3045.93,
        3033.63,
        3043.73
      ],
      "gb_predictions": [
        3003.89,
        2755.79,
        2639.71,
        2639.71,
        2701.52,
        3135.4
      ],
      "ci_lower": [
        2399.37,
        2051.46,
        1770.78,
        1636.65,
        1512.94,
        1582.86
      ],
      "ci_upper": [
        3625.85,
        3785.96,
        3895.1,
        4089.61,
        4255.42,
        4587.1
      ],
      "current_price": 2835.13,
      "ema_values": [
        2507.31,
        2533.5214,
        2544.1553,
        2701.1852,
        2671.7466,
        2645.7561,
        2625.5487,
        2713.5148,
        2830.3763,
        2898.103,
        2973.3679,
        3023.2799,
        3335.2628,
        3280.2363,
        3213.2173,
        3096.6638,
        3015.0513,
        2798.4166,
        2688.0833,
        2751.0995,
        2826.3997,
        2877.6655,
        3027.7982,
        3050.3787,
        3042.4076,
        3041.4512,
        2979.428,
        2793.66,
        2765.2571,
        2758.5522,
        2744.6802,
        3148.5973,
        3278.918,
        3300.2757,
        3338.2255,
        3194.484
      ],
      "volatility_pct": 14.42,
      "rsi": 48.25,
      "macd_line": 112.4983,
      "macd_signal": 94.7646,
      "macd_histogram": 17.7337,
      "bb_upper": 3864.73,
      "bb_mid": 2983.27,
      "bb_lower": 2101.81,
      "price_signal": "NEUTRAL",
      "signal_reason": "Mixed signals \u2014 monitor closely",
      "signal_color": "yellow",
      "pct_change_expected": 3.44,
      "method": "Ensemble: ARIMA(3,1,2) + Gradient Boosted Trees",
      "history_dates": [
        "2023-04",
        "2023-05",
        "2023-06",
        "2023-07",
        "2023-08",
        "2023-09",
        "2023-10",
        "2023-11",
        "2023-12",
        "2024-01",
        "2024-02",
        "2024-03",
        "2024-04",
        "2024-05",
        "2024-06",
        "2024-07",
        "2024-08",
        "2024-09",
        "2024-10",
        "2024-11",
        "2024-12",
        "2025-01",
        "2025-02",
        "2025-03",
        "2025-04",
        "2025-05",
        "2025-06",
        "2025-07",
        "2025-08",
        "2025-09",
        "2025-10",
        "2025-11",
        "2025-12",
        "2026-01",
        "2026-02",
        "2026-03"
      ],
      "history_values": [
        2507.31,
        2599.05,
        2570.74,
        3093.76,
        2598.15,
        2580.78,
        2575.03,
        2933.43,
        3122.53,
        3067.42,
        3161.53,
        3148.06,
        4115.22,
        3142.67,
        3045.67,
        2805.28,
        2811.02,
        2256.83,
        2412.25,
        2908.64,
        3014.65,
        3005.83,
        3403.13,
        3106.83,
        3022.48,
        3039.06,
        2824.37,
        2329.24,
        2694.25,
        2741.79,
        2710.0,
        4158.39,
        3604.72,
        3353.67,
        3433.1,
        2835.13
      ]
    },
    "Copper Wire": {
      "predictions": [
        10175.94,
        9337.89,
        9221.65,
        8837.75,
        8937.04,
        9353.69
      ],
      "arima_predictions": [
        9259.18,
        8752.51,
        8774.65,
        8724.45,
        8668.14,
        8601.24
      ],
      "gb_predictions": [
        11296.42,
        10053.35,
        9767.98,
        8976.23,
        9265.7,
        10273.35
      ],
      "ci_lower": [
        8095.54,
        6395.76,
        5618.29,
        4676.95,
        4285.12,
        4257.77
      ],
      "ci_upper": [
        12256.34,
        12280.02,
        12825.01,
        12998.55,
        13588.96,
        14449.61
      ],
      "current_price": 7970.88,
      "ema_values": [
        8880.06,
        9057.24,
        9355.8829,
        10198.7592,
        10049.7108,
        9953.3677,
        9625.9112,
        10049.7252,
        10280.9237,
        10371.1369,
        10638.3721,
        10919.4315,
        12148.6225,
        11550.3618,
        11303.5898,
        10871.8527,
        10508.9577,
        9791.0669,
        9488.4792,
        9263.0366,
        9199.3604,
        9213.5432,
        10110.828,
        10407.64,
        10579.1028,
        10465.7935,
        10378.2096,
        9380.9269,
        9116.1363,
        9059.4517,
        8747.4683,
        9955.8317,
        10080.0283,
        10372.3574,
        10503.5896,
        9779.9583
      ],
      "volatility_pct": 17.4,
      "rsi": 47.22,
      "macd_line": -19.4228,
      "macd_signal": 12.2137,
      "macd_histogram": -31.6365,
      "bb_upper": 12759.67,
      "bb_mid": 9683.6,
      "bb_lower": 6607.54,
      "price_signal": "NEUTRAL",
      "signal_reason": "Mixed signals \u2014 monitor closely",
      "signal_color": "yellow",
      "pct_change_expected": 16.81,
      "method": "Ensemble: ARIMA(3,1,2) + Gradient Boosted Trees",
      "history_dates": [
        "2023-04",
        "2023-05",
        "2023-06",
        "2023-07",
        "2023-08",
        "2023-09",
        "2023-10",
        "2023-11",
        "2023-12",
        "2024-01",
        "2024-02",
        "2024-03",
        "2024-04",
        "2024-05",
        "2024-06",
        "2024-07",
        "2024-08",
        "2024-09",
        "2024-10",
        "2024-11",
        "2024-12",
        "2025-01",
        "2025-02",
        "2025-03",
        "2025-04",
        "2025-05",
        "2025-06",
        "2025-07",
        "2025-08",
        "2025-09",
        "2025-10",
        "2025-11",
        "2025-12",
        "2026-01",
        "2026-02",
        "2026-03"
      ],
      "history_values": [
        8880.06,
        9500.19,
        10102.49,
        12305.95,
        9677.09,
        9712.51,
        8807.27,
        11109.26,
        10858.92,
        10596.67,
        11306.46,
        11622.08,
        15221.6,
        10054.71,
        10686.66,
        9792.51,
        9601.72,
        7996.34,
        8732.01,
        8699.43,
        9040.17,
        9249.0,
        12354.04,
        11149.67,
        11007.76,
        10182.52,
        10159.25,
        6887.72,
        8454.16,
        8917.74,
        7967.51,
        12976.74,
        10390.52,
        11103.18,
        10831.67,
        7970.88
      ]
    },
    "Plastic Pellets": {
      "predictions": [
        1036.83,
        1045.89,
        1068.24,
        1111.55,
        1136.84,
        1140.17
      ],
      "arima_predictions": [
        1050.98,
        1064.36,
        1036.75,
        1048.04,
        1024.2,
        1032.08
      ],
      "gb_predictions": [
        1019.54,
        1023.31,
        1106.72,
        1189.17,
        1274.52,
        1272.28
      ],
      "ci_lower": [
        806.64,
        720.35,
        669.54,
        651.17,
        622.12,
        576.32
      ],
      "ci_upper": [
        1267.02,
        1371.43,
        1466.94,
        1571.93,
        1651.56,
        1704.02
      ],
      "current_price": 1051.82,
      "ema_values": [
        1253.65,
        1237.7786,
        1241.8933,
        1288.7266,
        1287.8047,
        1255.9062,
        1216.5873,
        1217.3081,
        1204.1801,
        1195.4972,
        1169.8894,
        1157.301,
        1213.1007,
        1210.0148,
        1260.2591,
        1295.6737,
        1242.9555,
        1150.5796,
        1079.9997,
        1025.4341,
        993.2701,
        970.0043,
        1021.6231,
        1067.1479,
        1098.8799,
        1121.2371,
        1124.7008,
        1040.4177,
        994.4326,
        970.5576,
        957.164,
        1073.4514,
        1139.3682,
        1205.1087,
        1258.3519,
        1199.3428
      ],
      "volatility_pct": 14.59,
      "rsi": 54.26,
      "macd_line": 16.2386,
      "macd_signal": -13.1636,
      "macd_histogram": 29.4022,
      "bb_upper": 1436.75,
      "bb_mid": 1074.66,
      "bb_lower": 712.57,
      "price_signal": "NEUTRAL",
      "signal_reason": "Mixed signals \u2014 monitor closely",
      "signal_color": "yellow",
      "pct_change_expected": 3.62,
      "method": "Ensemble: ARIMA(3,1,2) + Gradient Boosted Trees",
      "history_dates": [
        "2023-04",
        "2023-05",
        "2023-06",
        "2023-07",
        "2023-08",
        "2023-09",
        "2023-10",
        "2023-11",
        "2023-12",
        "2024-01",
        "2024-02",
        "2024-03",
        "2024-04",
        "2024-05",
        "2024-06",
        "2024-07",
        "2024-08",
        "2024-09",
        "2024-10",
        "2024-11",
        "2024-12",
        "2025-01",
        "2025-02",
        "2025-03",
        "2025-04",
        "2025-05",
        "2025-06",
        "2025-07",
        "2025-08",
        "2025-09",
        "2025-10",
        "2025-11",
        "2025-12",
        "2026-01",
        "2026-02",
        "2026-03"
      ],
      "history_values": [
        1253.65,
        1198.1,
        1252.18,
        1405.81,
        1285.5,
        1176.16,
        1118.29,
        1219.11,
        1171.36,
        1173.79,
        1105.87,
        1125.83,
        1352.6,
        1202.3,
        1385.87,
        1384.21,
        1111.16,
        919.64,
        903.55,
        889.02,
        912.86,
        911.84,
        1150.67,
        1180.96,
        1178.21,
        1177.13,
        1133.36,
        829.71,
        879.47,
        910.87,
        923.68,
        1364.17,
        1304.16,
        1369.46,
        1391.46,
        1051.82
      ]
    },
    "Carbon Fiber": {
      "predictions": [
        26885.92,
        26475.21,
        26501.5,
        26146.42,
        25653.68,
        25068.18
      ],
      "arima_predictions": [
        27384.47,
        26637.73,
        25982.58,
        25146.71,
        24250.82,
        23186.28
      ],
      "gb_predictions": [
        26276.57,
        26276.57,
        27135.73,
        27368.28,
        27368.28,
        27368.28
      ],
      "ci_lower": [
        21947.63,
        19491.42,
        17948.14,
        16269.85,
        14611.33,
        12971.9
      ],
      "ci_upper": [
        31824.21,
        33459.0,
        35054.86,
        36022.99,
        36696.03,
        37164.46
      ],
      "current_price": 28162.46,
      "ema_values": [
        22983.67,
        23190.1329,
        22768.4892,
        23094.4723,
        23092.6716,
        22888.5797,
        22647.7712,
        22711.5395,
        22107.0539,
        21946.9928,
        22415.4263,
        23152.4359,
        23971.9656,
        23628.864,
        23308.6657,
        22341.987,
        21006.7964,
        19717.7146,
        18605.999,
        18359.7707,
        18707.4076,
        18582.914,
        19819.1986,
        20883.0047,
        20955.6948,
        21376.9163,
        21840.4716,
        21642.1683,
        21549.9202,
        21671.9287,
        22118.9834,
        24630.8396,
        27123.1854,
        28934.2467,
        29397.7848,
        29044.8349
      ],
      "volatility_pct": 11.69,
      "rsi": 67.05,
      "macd_line": 2292.4249,
      "macd_signal": 1244.4244,
      "macd_histogram": 1048.0005,
      "bb_upper": 33700.13,
      "bb_mid": 23136.35,
      "bb_lower": 12572.56,
      "price_signal": "NEUTRAL",
      "signal_reason": "Mixed signals \u2014 monitor closely",
      "signal_color": "yellow",
      "pct_change_expected": -7.25,
      "method": "Ensemble: ARIMA(3,1,2) + Gradient Boosted Trees",
      "history_dates": [
        "2023-04",
        "2023-05",
        "2023-06",
        "2023-07",
        "2023-08",
        "2023-09",
        "2023-10",
        "2023-11",
        "2023-12",
        "2024-01",
        "2024-02",
        "2024-03",
        "2024-04",
        "2024-05",
        "2024-06",
        "2024-07",
        "2024-08",
        "2024-09",
        "2024-10",
        "2024-11",
        "2024-12",
        "2025-01",
        "2025-02",
        "2025-03",
        "2025-04",
        "2025-05",
        "2025-06",
        "2025-07",
        "2025-08",
        "2025-09",
        "2025-10",
        "2025-11",
        "2025-12",
        "2026-01",
        "2026-02",
        "2026-03"
      ],
      "history_values": [
        22983.67,
        23706.29,
        21714.38,
        23909.43,
        23088.17,
        22378.35,
        22045.75,
        22870.96,
        20595.84,
        21546.84,
        23586.51,
        24994.96,
        26020.79,
        22771.11,
        22508.17,
        19925.29,
        17668.82,
        16495.01,
        15826.71,
        17744.2,
        19576.5,
        18271.68,
        22909.91,
        23542.52,
        21137.42,
        22429.97,
        22999.36,
        21146.41,
        21319.3,
        21976.95,
        23236.62,
        30910.48,
        33354.05,
        33461.9,
        30556.63,
        28162.46
      ]
    },
    "Silicon Wafers": {
      "predictions": [
        17869.56,
        16502.44,
        15751.93,
        17165.61,
        16327.6,
        16815.08
      ],
      "arima_predictions": [
        16492.81,
        15798.96,
        15424.75,
        15776.22,
        15311.69,
        15419.89
      ],
      "gb_predictions": [
        19552.26,
        17362.26,
        16151.82,
        18863.76,
        17569.27,
        18520.32
      ],
      "ci_lower": [
        14472.12,
        11697.73,
        9867.39,
        10370.73,
        8730.69,
        8493.08
      ],
      "ci_upper": [
        21267.0,
        21307.15,
        21636.47,
        23960.49,
        23924.51,
        25137.08
      ],
      "current_price": 13904.0,
      "ema_values": [
        15670.69,
        15794.2214,
        16151.1324,
        17981.2746,
        17620.959,
        18010.7564,
        17738.1117,
        18316.2141,
        18006.8901,
        17766.4472,
        17428.1709,
        17459.4906,
        19051.399,
        18606.4136,
        18037.9668,
        17560.7277,
        17238.3427,
        16551.6905,
        16574.6389,
        16728.5364,
        17741.3231,
        18359.5908,
        20711.1191,
        21228.7165,
        20871.1032,
        20908.8709,
        21091.9706,
        19538.0305,
        19078.4989,
        18882.6678,
        18149.6141,
        19751.7958,
        19426.637,
        19171.6693,
        19075.6666,
        17598.0476
      ],
      "volatility_pct": 16.29,
      "rsi": 43.1,
      "macd_line": -92.4109,
      "macd_signal": 417.8484,
      "macd_histogram": -510.2593,
      "bb_upper": 25035.56,
      "bb_mid": 18938.59,
      "bb_lower": 12841.63,
      "price_signal": "NEUTRAL",
      "signal_reason": "Mixed signals \u2014 monitor closely",
      "signal_color": "yellow",
      "pct_change_expected": 20.39,
      "method": "Ensemble: ARIMA(3,1,2) + Gradient Boosted Trees",
      "history_dates": [
        "2023-04",
        "2023-05",
        "2023-06",
        "2023-07",
        "2023-08",
        "2023-09",
        "2023-10",
        "2023-11",
        "2023-12",
        "2024-01",
        "2024-02",
        "2024-03",
        "2024-04",
        "2024-05",
        "2024-06",
        "2024-07",
        "2024-08",
        "2024-09",
        "2024-10",
        "2024-11",
        "2024-12",
        "2025-01",
        "2025-02",
        "2025-03",
        "2025-04",
        "2025-05",
        "2025-06",
        "2025-07",
        "2025-08",
        "2025-09",
        "2025-10",
        "2025-11",
        "2025-12",
        "2026-01",
        "2026-02",
        "2026-03"
      ],
      "history_values": [
        15670.69,
        16103.05,
        17043.41,
        22556.63,
        16720.17,
        18985.25,
        17056.5,
        19761.47,
        17233.58,
        17165.34,
        16582.48,
        17537.79,
        23031.17,
        17493.95,
        16616.85,
        16367.63,
        16432.38,
        14835.06,
        16632.01,
        17113.28,
        20273.29,
        19905.26,
        26589.94,
        22522.71,
        19977.07,
        21003.29,
        21549.72,
        15653.18,
        17929.67,
        18393.09,
        16316.98,
        23757.25,
        18613.74,
        18534.25,
        18835.66,
        13904.0
      ]
    },
    "Titanium Alloy": {
      "predictions": [
        27479.61,
        23287.87,
        22174.92,
        17678.99,
        16673.38,
        16725.13
      ],
      "arima_predictions": [
        24997.01,
        17363.92,
        10448.47,
        1828.38,
        0,
        0
      ],
      "gb_predictions": [
        30513.9,
        30528.25,
        36507.25,
        37051.96,
        37051.96,
        37166.95
      ],
      "ci_lower": [
        21198.61,
        14405.19,
        11295.91,
        5116.99,
        2628.63,
        1339.88
      ],
      "ci_upper": [
        33760.61,
        32170.55,
        33053.93,
        30240.99,
        30718.13,
        32110.38
      ],
      "current_price": 28778.93,
      "ema_values": [
        36564.94,
        36754.5829,
        37393.4163,
        38135.1174,
        36964.4038,
        36760.6313,
        35154.9424,
        35667.3274,
        35794.8739,
        35978.467,
        34998.1679,
        34920.7913,
        37048.591,
        36531.525,
        35863.6007,
        34829.7948,
        33445.3334,
        31340.3696,
        30117.364,
        29771.2486,
        29835.589,
        29425.7607,
        31580.4405,
        32333.0632,
        34245.6366,
        35196.5461,
        35624.9044,
        33616.726,
        32554.09,
        31610.0957,
        31390.9684,
        34322.2974,
        36640.7639,
        37782.5456,
        38391.1526,
        35644.8033
      ],
      "volatility_pct": 14.55,
      "rsi": 50.34,
      "macd_line": 523.901,
      "macd_signal": 207.2865,
      "macd_histogram": 316.6145,
      "bb_upper": 43933.15,
      "bb_mid": 33345.36,
      "bb_lower": 22757.57,
      "price_signal": "NEUTRAL",
      "signal_reason": "Mixed signals \u2014 monitor closely",
      "signal_color": "yellow",
      "pct_change_expected": -28.18,
      "method": "Ensemble: ARIMA(3,1,2) + Gradient Boosted Trees",
      "history_dates": [
        "2023-04",
        "2023-05",
        "2023-06",
        "2023-07",
        "2023-08",
        "2023-09",
        "2023-10",
        "2023-11",
        "2023-12",
        "2024-01",
        "2024-02",
        "2024-03",
        "2024-04",
        "2024-05",
        "2024-06",
        "2024-07",
        "2024-08",
        "2024-09",
        "2024-10",
        "2024-11",
        "2024-12",
        "2025-01",
        "2025-02",
        "2025-03",
        "2025-04",
        "2025-05",
        "2025-06",
        "2025-07",
        "2025-08",
        "2025-09",
        "2025-10",
        "2025-11",
        "2025-12",
        "2026-01",
        "2026-02",
        "2026-03"
      ],
      "history_values": [
        36564.94,
        37228.69,
        38990.5,
        39989.37,
        34037.62,
        36251.2,
        31140.72,
        36948.29,
        36113.74,
        36437.45,
        32547.42,
        34727.35,
        42368.09,
        35238.86,
        34193.79,
        32245.28,
        29984.18,
        26077.96,
        27059.85,
        28905.96,
        29996.44,
        28401.19,
        36967.14,
        34214.62,
        39027.07,
        37573.82,
        36695.8,
        28596.28,
        29897.5,
        29250.11,
        30843.15,
        41650.62,
        42436.93,
        40637.0,
        39912.67,
        28778.93
      ]
    },
    "Nickel Powder": {
      "predictions": [
        17275.28,
        16420.61,
        17856.07,
        16247.93,
        18251.14,
        15944.03
      ],
      "arima_predictions": [
        18001.07,
        17207.89,
        18038.3,
        16820.42,
        18401.01,
        16033.74
      ],
      "gb_predictions": [
        16388.2,
        15458.39,
        17633.35,
        15548.23,
        18067.97,
        15834.39
      ],
      "ci_lower": [
        13557.11,
        11162.32,
        11416.01,
        8811.58,
        9937.05,
        6836.4
      ],
      "ci_upper": [
        20993.45,
        21678.9,
        24296.13,
        23684.28,
        26565.23,
        25051.66
      ],
      "current_price": 15521.49,
      "ema_values": [
        18804.82,
        18507.3971,
        18411.7665,
        19124.459,
        18111.605,
        17678.6207,
        17270.8205,
        18351.0775,
        18630.9896,
        17958.2555,
        18432.2139,
        18905.5099,
        20551.0214,
        20033.1867,
        20255.6905,
        20024.5904,
        19505.3617,
        17869.3412,
        17226.1237,
        16863.5055,
        16889.0439,
        16797.9457,
        18580.6469,
        18134.0821,
        17726.8701,
        17184.5215,
        17197.481,
        15415.9236,
        14657.294,
        14082.8157,
        14205.5169,
        16543.8721,
        17343.1086,
        18410.8176,
        19374.1669,
        18273.402
      ],
      "volatility_pct": 15.97,
      "rsi": 48.83,
      "macd_line": 101.7633,
      "macd_signal": -298.6397,
      "macd_histogram": 400.403,
      "bb_upper": 23353.7,
      "bb_mid": 16895.19,
      "bb_lower": 10436.69,
      "price_signal": "BUY NOW",
      "signal_reason": "Price projected to rise 9.5% | MACD bullish crossover",
      "signal_color": "red",
      "pct_change_expected": 9.52,
      "method": "Ensemble: ARIMA(3,1,2) + Gradient Boosted Trees",
      "history_dates": [
        "2023-04",
        "2023-05",
        "2023-06",
        "2023-07",
        "2023-08",
        "2023-09",
        "2023-10",
        "2023-11",
        "2023-12",
        "2024-01",
        "2024-02",
        "2024-03",
        "2024-04",
        "2024-05",
        "2024-06",
        "2024-07",
        "2024-08",
        "2024-09",
        "2024-10",
        "2024-11",
        "2024-12",
        "2025-01",
        "2025-02",
        "2025-03",
        "2025-04",
        "2025-05",
        "2025-06",
        "2025-07",
        "2025-08",
        "2025-09",
        "2025-10",
        "2025-11",
        "2025-12",
        "2026-01",
        "2026-02",
        "2026-03"
      ],
      "history_values": [
        18804.82,
        17763.84,
        18172.69,
        20906.19,
        15579.47,
        16596.16,
        16251.32,
        21051.72,
        19330.77,
        16276.42,
        19617.11,
        20088.75,
        24664.8,
        18738.6,
        20811.95,
        19446.84,
        18207.29,
        13779.29,
        15618.08,
        15956.96,
        16952.89,
        16570.2,
        23037.4,
        17017.67,
        16708.84,
        15828.65,
        17229.88,
        10962.03,
        12760.72,
        12646.62,
        14512.27,
        22389.76,
        19341.2,
        21080.09,
        21782.54,
        15521.49
      ]
    },
    "Graphite Electrodes": {
      "predictions": [
        5097.69,
        4957.37,
        5416.9,
        5333.23,
        5002.45,
        4762.87
      ],
      "arima_predictions": [
        4693.38,
        4399.92,
        4439.83,
        4408.78,
        4341.5,
        4338.67
      ],
      "gb_predictions": [
        5591.85,
        5638.7,
        6611.09,
        6463.11,
        5810.27,
        5281.33
      ],
      "ci_lower": [
        4071.14,
        3505.61,
        3638.86,
        3280.13,
        2707.01,
        2248.34
      ],
      "ci_upper": [
        6124.24,
        6409.13,
        7194.94,
        7386.33,
        7297.89,
        7277.4
      ],
      "current_price": 4162.82,
      "ema_values": [
        4701.21,
        4746.21,
        4861.3186,
        5256.6133,
        5237.0466,
        5395.7104,
        5393.3417,
        5707.1012,
        5887.8237,
        5956.0027,
        6073.9619,
        6339.8557,
        6797.354,
        6672.0129,
        6516.2806,
        6268.329,
        6040.535,
        5549.4993,
        5314.5938,
        5099.7327,
        5179.2148,
        5210.7077,
        5791.6769,
        5881.9292,
        5910.098,
        5933.7214,
        6070.9067,
        5637.822,
        5607.6157,
        5489.5141,
        5298.0958,
        5808.1427,
        5781.9391,
        5782.3736,
        5674.0869,
        5242.2963
      ],
      "volatility_pct": 16.44,
      "rsi": 45.5,
      "macd_line": -87.9402,
      "macd_signal": 32.0516,
      "macd_histogram": -119.9918,
      "bb_upper": 7131.47,
      "bb_mid": 5486.97,
      "bb_lower": 3842.47,
      "price_signal": "NEUTRAL",
      "signal_reason": "Mixed signals \u2014 monitor closely",
      "signal_color": "yellow",
      "pct_change_expected": 22.4,
      "method": "Ensemble: ARIMA(3,1,2) + Gradient Boosted Trees",
      "history_dates": [
        "2023-04",
        "2023-05",
        "2023-06",
        "2023-07",
        "2023-08",
        "2023-09",
        "2023-10",
        "2023-11",
        "2023-12",
        "2024-01",
        "2024-02",
        "2024-03",
        "2024-04",
        "2024-05",
        "2024-06",
        "2024-07",
        "2024-08",
        "2024-09",
        "2024-10",
        "2024-11",
        "2024-12",
        "2025-01",
        "2025-02",
        "2025-03",
        "2025-04",
        "2025-05",
        "2025-06",
        "2025-07",
        "2025-08",
        "2025-09",
        "2025-10",
        "2025-11",
        "2025-12",
        "2026-01",
        "2026-02",
        "2026-03"
      ],
      "history_values": [
        4701.21,
        4858.71,
        5149.09,
        6244.85,
        5188.13,
        5792.37,
        5387.42,
        6491.5,
        6339.63,
        6126.45,
        6368.86,
        7004.59,
        7941.1,
        6358.66,
        6126.95,
        5648.45,
        5471.05,
        4321.91,
        4727.33,
        4562.58,
        5377.92,
        5289.44,
        7244.1,
        6107.56,
        5980.52,
        5992.78,
        6413.87,
        4555.11,
        5532.1,
        5194.26,
        4819.55,
        7083.26,
        5716.43,
        5783.46,
        5403.37,
        4162.82
      ]
    },
    "Rare Earth Magnets": {
      "predictions": [
        90462.79,
        83401.44,
        90606.06,
        83968.01,
        92161.19,
        81940.11
      ],
      "arima_predictions": [
        89211.52,
        76116.51,
        87313.74,
        73891.07,
        88787.76,
        70203.97
      ],
      "gb_predictions": [
        91992.11,
        92305.25,
        94630.01,
        96284.28,
        96284.28,
        96284.28
      ],
      "ci_lower": [
        67473.2,
        50889.25,
        50786.92,
        37988.83,
        40754.9,
        25627.34
      ],
      "ci_upper": [
        113452.38,
        115913.63,
        130425.2,
        129947.19,
        143567.48,
        138252.88
      ],
      "current_price": 67546.91,
      "ema_values": [
        88800.56,
        88564.5657,
        88121.4527,
        93991.5862,
        89309.2673,
        87676.9252,
        84643.9637,
        87648.6341,
        86592.4472,
        87002.9537,
        85635.1869,
        86653.7478,
        93800.1399,
        91173.2085,
        93464.1032,
        93443.6451,
        93356.1522,
        89968.7545,
        88462.2503,
        87956.6931,
        85975.8494,
        84951.2181,
        96521.0729,
        100413.7892,
        102597.2123,
        102838.3888,
        103766.6463,
        95673.5502,
        93453.1244,
        92003.7003,
        90321.1688,
        105015.9577,
        106101.8041,
        103385.7229,
        101987.4164,
        92147.2717
      ],
      "volatility_pct": 22.69,
      "rsi": 47.0,
      "macd_line": 438.0486,
      "macd_signal": 2414.4425,
      "macd_histogram": -1976.3939,
      "bb_upper": 130114.64,
      "bb_mid": 95682.84,
      "bb_lower": 61251.04,
      "price_signal": "NEUTRAL",
      "signal_reason": "Mixed signals \u2014 monitor closely",
      "signal_color": "yellow",
      "pct_change_expected": 28.93,
      "method": "Ensemble: ARIMA(3,1,2) + Gradient Boosted Trees",
      "history_dates": [
        "2023-04",
        "2023-05",
        "2023-06",
        "2023-07",
        "2023-08",
        "2023-09",
        "2023-10",
        "2023-11",
        "2023-12",
        "2024-01",
        "2024-02",
        "2024-03",
        "2024-04",
        "2024-05",
        "2024-06",
        "2024-07",
        "2024-08",
        "2024-09",
        "2024-10",
        "2024-11",
        "2024-12",
        "2025-01",
        "2025-02",
        "2025-03",
        "2025-04",
        "2025-05",
        "2025-06",
        "2025-07",
        "2025-08",
        "2025-09",
        "2025-10",
        "2025-11",
        "2025-12",
        "2026-01",
        "2026-02",
        "2026-03"
      ],
      "history_values": [
        88800.56,
        87974.58,
        87013.67,
        108666.92,
        77603.47,
        83596.07,
        77061.56,
        95160.31,
        83951.98,
        88029.22,
        82215.77,
        89200.15,
        111666.12,
        84605.88,
        99191.34,
        93392.5,
        93137.42,
        81500.26,
        84695.99,
        86692.8,
        81023.74,
        82389.64,
        125445.71,
        110145.58,
        108055.77,
        103441.33,
        106087.29,
        75440.81,
        87902.06,
        88380.14,
        86114.84,
        141752.93,
        108816.42,
        96595.52,
        98491.65,
        67546.91
      ]
    }
  },
  "recommendations": [
    {
      "material": "Carbon Fiber",
      "action": "ORDER IMMEDIATELY",
      "priority": "Critical",
      "timing": "Today",
      "recommended_qty": 0,
      "recommended_supplier": "ToraySource",
      "supplier_score": 94.85,
      "supplier_grade": "A+",
      "alt_supplier": "FiberTech",
      "split_order_suggestion": null,
      "current_price": 28162.46,
      "price_signal": "NEUTRAL",
      "price_trend_pct": -8.63,
      "volatility_pct": 11.69,
      "demand_trend": "Decreasing",
      "demand_forecast_3mo": [
        30,
        9,
        9
      ],
      "inventory_level": "Critical",
      "urgency_score": 90,
      "decision_score": 44.1,
      "dynamic_days_of_supply": 1733,
      "stockout_probability": 0.0,
      "eoq": 222,
      "safety_stock": 37,
      "estimated_savings": 0,
      "reason": "Inventory: Critical | Price: NEUTRAL | Demand: Decreasing",
      "lead_time_days": 18,
      "budget_allocated": true,
      "allocated_qty": 0,
      "estimated_cost": 0
    },
    {
      "material": "Plastic Pellets",
      "action": "PLACE ORDER",
      "priority": "High",
      "timing": "This Week",
      "recommended_qty": 236,
      "recommended_supplier": "PolyBase Inc",
      "supplier_score": 89.68,
      "supplier_grade": "A",
      "alt_supplier": "PlastiCore",
      "split_order_suggestion": {
        "primary": {
          "supplier": "PolyBase Inc",
          "qty": 153
        },
        "alternate": {
          "supplier": "PlastiCore",
          "qty": 83
        }
      },
      "current_price": 1051.82,
      "price_signal": "NEUTRAL",
      "price_trend_pct": 3.7,
      "volatility_pct": 14.59,
      "demand_trend": "Increasing",
      "demand_forecast_3mo": [
        324,
        342,
        401
      ],
      "inventory_level": "Low",
      "urgency_score": 65,
      "decision_score": 36.6,
      "dynamic_days_of_supply": 219,
      "stockout_probability": 0.0,
      "eoq": 553,
      "safety_stock": 430,
      "estimated_savings": 0,
      "reason": "Inventory: Low | Price: NEUTRAL | Demand: Increasing",
      "lead_time_days": 18,
      "budget_allocated": true,
      "allocated_qty": 236,
      "estimated_cost": 248229.52,
      "remaining_budget_after": 4751770.48
    },
    {
      "material": "Nickel Powder",
      "action": "OPPORTUNISTIC BUY \u2014 Favourable price window",
      "priority": "Medium",
      "timing": "Next 2 Weeks",
      "recommended_qty": 0,
      "recommended_supplier": "NickelBase",
      "supplier_score": 93.29,
      "supplier_grade": "A+",
      "alt_supplier": "BatteryMat Supply",
      "split_order_suggestion": null,
      "current_price": 15521.49,
      "price_signal": "BUY NOW",
      "price_trend_pct": 10.54,
      "volatility_pct": 15.97,
      "demand_trend": "Increasing",
      "demand_forecast_3mo": [
        52,
        38,
        27
      ],
      "inventory_level": "Adequate",
      "urgency_score": 10,
      "decision_score": 15.5,
      "dynamic_days_of_supply": 4396,
      "stockout_probability": 0.0,
      "eoq": 258,
      "safety_stock": 90,
      "estimated_savings": 0.0,
      "reason": "Inventory: Adequate | Price: BUY NOW | Demand: Increasing",
      "lead_time_days": 15,
      "budget_allocated": true,
      "allocated_qty": 0,
      "estimated_cost": 0
    },
    {
      "material": "Silicon Wafers",
      "action": "MONITOR \u2014 No urgent action needed",
      "priority": "Low",
      "timing": "Within Month",
      "recommended_qty": 0,
      "recommended_supplier": "WaferTech",
      "supplier_score": 92.39,
      "supplier_grade": "A+",
      "alt_supplier": "ChipSource Asia",
      "split_order_suggestion": null,
      "current_price": 13904.0,
      "price_signal": "NEUTRAL",
      "price_trend_pct": 20.42,
      "volatility_pct": 16.29,
      "demand_trend": "Increasing",
      "demand_forecast_3mo": [
        82,
        138,
        88
      ],
      "inventory_level": "Adequate",
      "urgency_score": 10,
      "decision_score": 13.6,
      "dynamic_days_of_supply": 4922,
      "stockout_probability": 0.0,
      "eoq": 356,
      "safety_stock": 93,
      "estimated_savings": 0,
      "reason": "Inventory: Adequate | Price: NEUTRAL | Demand: Increasing",
      "lead_time_days": 6,
      "budget_allocated": true,
      "allocated_qty": 0,
      "estimated_cost": 0
    },
    {
      "material": "Rare Earth Magnets",
      "action": "MONITOR \u2014 No urgent action needed",
      "priority": "Low",
      "timing": "Within Month",
      "recommended_qty": 0,
      "recommended_supplier": "MagnetCore",
      "supplier_score": 93.31,
      "supplier_grade": "A+",
      "alt_supplier": "AsiaRareMetal",
      "split_order_suggestion": null,
      "current_price": 67546.91,
      "price_signal": "NEUTRAL",
      "price_trend_pct": 28.98,
      "volatility_pct": 22.69,
      "demand_trend": "Decreasing",
      "demand_forecast_3mo": [
        22,
        20,
        18
      ],
      "inventory_level": "Adequate",
      "urgency_score": 10,
      "decision_score": 11.9,
      "dynamic_days_of_supply": 9125,
      "stockout_probability": 0.0,
      "eoq": 522,
      "safety_stock": 13,
      "estimated_savings": 0,
      "reason": "Inventory: Adequate | Price: NEUTRAL | Demand: Decreasing",
      "lead_time_days": 22,
      "budget_allocated": true,
      "allocated_qty": 0,
      "estimated_cost": 0
    },
    {
      "material": "Copper Wire",
      "action": "MONITOR \u2014 No urgent action needed",
      "priority": "Low",
      "timing": "Within Month",
      "recommended_qty": 0,
      "recommended_supplier": "CopperKing",
      "supplier_score": 92.35,
      "supplier_grade": "A+",
      "alt_supplier": "WireWorks Ltd",
      "split_order_suggestion": null,
      "current_price": 7970.88,
      "price_signal": "NEUTRAL",
      "price_trend_pct": 16.8,
      "volatility_pct": 17.4,
      "demand_trend": "Decreasing",
      "demand_forecast_3mo": [
        169,
        90,
        106
      ],
      "inventory_level": "Adequate",
      "urgency_score": 10,
      "decision_score": 11.2,
      "dynamic_days_of_supply": 571,
      "stockout_probability": 0.0,
      "eoq": 2930,
      "safety_stock": 109,
      "estimated_savings": 0,
      "reason": "Inventory: Adequate | Price: NEUTRAL | Demand: Decreasing",
      "lead_time_days": 24,
      "budget_allocated": true,
      "allocated_qty": 0,
      "estimated_cost": 0
    },
    {
      "material": "Graphite Electrodes",
      "action": "MONITOR \u2014 No urgent action needed",
      "priority": "Low",
      "timing": "Within Month",
      "recommended_qty": 0,
      "recommended_supplier": "GraphCo",
      "supplier_score": 90.89,
      "supplier_grade": "A+",
      "alt_supplier": "CarbonTech",
      "split_order_suggestion": null,
      "current_price": 4162.82,
      "price_signal": "NEUTRAL",
      "price_trend_pct": 22.4,
      "volatility_pct": 16.44,
      "demand_trend": "Decreasing",
      "demand_forecast_3mo": [
        49,
        20,
        12
      ],
      "inventory_level": "Adequate",
      "urgency_score": 10,
      "decision_score": 11.0,
      "dynamic_days_of_supply": 3220,
      "stockout_probability": 0.0,
      "eoq": 544,
      "safety_stock": 99,
      "estimated_savings": 0,
      "reason": "Inventory: Adequate | Price: NEUTRAL | Demand: Decreasing",
      "lead_time_days": 28,
      "budget_allocated": true,
      "allocated_qty": 0,
      "estimated_cost": 0
    },
    {
      "material": "Aluminum Sheets",
      "action": "MONITOR \u2014 No urgent action needed",
      "priority": "Low",
      "timing": "Within Month",
      "recommended_qty": 0,
      "recommended_supplier": "LightMetal Corp",
      "supplier_score": 94.95,
      "supplier_grade": "A+",
      "alt_supplier": "AlloySource Co",
      "split_order_suggestion": null,
      "current_price": 2835.13,
      "price_signal": "NEUTRAL",
      "price_trend_pct": 4.04,
      "volatility_pct": 14.42,
      "demand_trend": "Decreasing",
      "demand_forecast_3mo": [
        7,
        7,
        7
      ],
      "inventory_level": "Adequate",
      "urgency_score": 10,
      "decision_score": 10.5,
      "dynamic_days_of_supply": 7843,
      "stockout_probability": 0.0,
      "eoq": 544,
      "safety_stock": 180,
      "estimated_savings": 0,
      "reason": "Inventory: Adequate | Price: NEUTRAL | Demand: Decreasing",
      "lead_time_days": 18,
      "budget_allocated": true,
      "allocated_qty": 0,
      "estimated_cost": 0
    },
    {
      "material": "Titanium Alloy",
      "action": "MONITOR \u2014 No urgent action needed",
      "priority": "Low",
      "timing": "Within Month",
      "recommended_qty": 0,
      "recommended_supplier": "TitanWorks",
      "supplier_score": 96.56,
      "supplier_grade": "A+",
      "alt_supplier": "PrecisionMetal Co",
      "split_order_suggestion": null,
      "current_price": 28778.93,
      "price_signal": "NEUTRAL",
      "price_trend_pct": -28.05,
      "volatility_pct": 14.55,
      "demand_trend": "Decreasing",
      "demand_forecast_3mo": [
        24,
        20,
        16
      ],
      "inventory_level": "Adequate",
      "urgency_score": 10,
      "decision_score": 10.5,
      "dynamic_days_of_supply": 2477,
      "stockout_probability": 0.0,
      "eoq": 402,
      "safety_stock": 24,
      "estimated_savings": 0,
      "reason": "Inventory: Adequate | Price: NEUTRAL | Demand: Decreasing",
      "lead_time_days": 11,
      "budget_allocated": true,
      "allocated_qty": 0,
      "estimated_cost": 0
    },
    {
      "material": "Steel Coils",
      "action": "MONITOR \u2014 No urgent action needed",
      "priority": "Low",
      "timing": "Within Month",
      "recommended_qty": 0,
      "recommended_supplier": "IronBridge Supply",
      "supplier_score": 92.33,
      "supplier_grade": "A+",
      "alt_supplier": "SteelMart Inc",
      "split_order_suggestion": null,
      "current_price": 751.2,
      "price_signal": "BUY NOW",
      "price_trend_pct": 6.71,
      "volatility_pct": 13.57,
      "demand_trend": "Decreasing",
      "demand_forecast_3mo": [
        363,
        282,
        222
      ],
      "inventory_level": "Overstocked",
      "urgency_score": 5,
      "decision_score": 9.5,
      "dynamic_days_of_supply": 858,
      "stockout_probability": 0.0,
      "eoq": 1407,
      "safety_stock": 216,
      "estimated_savings": 0.0,
      "reason": "Inventory: Overstocked | Price: BUY NOW | Demand: Decreasing",
      "lead_time_days": 21,
      "budget_allocated": true,
      "allocated_qty": 0,
      "estimated_cost": 0
    }
  ],
  "materials": [
    "Steel Coils",
    "Aluminum Sheets",
    "Copper Wire",
    "Plastic Pellets",
    "Carbon Fiber",
    "Silicon Wafers",
    "Titanium Alloy",
    "Nickel Powder",
    "Graphite Electrodes",
    "Rare Earth Magnets"
  ]
}