{
  "generated_at": "2026-04-13T16:27:15.287421",
  "version": "2.0",
  "materials": [
    "Steel Coils",
    "Aluminum Sheets",
    "Copper Wire",
    "Plastic Pellets",
    "Carbon Fiber",
    "Silicon Wafers",
    "Titanium Alloy",
    "Nickel Powder",
    "Graphite Electrodes",
    "Rare Earth Magnets"
  ],
  "price_history": {
    "Steel Coils": [
      {
        "date": "2023-04",
        "price": 856.66
      },
      {
        "date": "2023-05",
        "price": 757.79
      },
      {
        "date": "2023-06",
        "price": 792.0
      },
      {
        "date": "2023-07",
        "price": 876.26
      },
      {
        "date": "2023-08",
        "price": 839.01
      },
      {
        "date": "2023-09",
        "price": 796.63
      },
      {
        "date": "2023-10",
        "price": 815.25
      },
      {
        "date": "2023-11",
        "price": 913.75
      },
      {
        "date": "2023-12",
        "price": 933.39
      },
      {
        "date": "2024-01",
        "price": 942.76
      },
      {
        "date": "2024-02",
        "price": 899.75
      },
      {
        "date": "2024-03",
        "price": 869.99
      },
      {
        "date": "2024-04",
        "price": 1101.75
      },
      {
        "date": "2024-05",
        "price": 945.33
      },
      {
        "date": "2024-06",
        "price": 939.6
      },
      {
        "date": "2024-07",
        "price": 846.91
      },
      {
        "date": "2024-08",
        "price": 766.34
      },
      {
        "date": "2024-09",
        "price": 656.15
      },
      {
        "date": "2024-10",
        "price": 513.04
      },
      {
        "date": "2024-11",
        "price": 580.64
      },
      {
        "date": "2024-12",
        "price": 739.96
      },
      {
        "date": "2025-01",
        "price": 669.81
      },
      {
        "date": "2025-02",
        "price": 892.34
      },
      {
        "date": "2025-03",
        "price": 871.59
      },
      {
        "date": "2025-04",
        "price": 816.18
      },
      {
        "date": "2025-05",
        "price": 823.52
      },
      {
        "date": "2025-06",
        "price": 898.38
      },
      {
        "date": "2025-07",
        "price": 714.19
      },
      {
        "date": "2025-08",
        "price": 795.43
      },
      {
        "date": "2025-09",
        "price": 801.43
      },
      {
        "date": "2025-10",
        "price": 787.97
      },
      {
        "date": "2025-11",
        "price": 1123.95
      },
      {
        "date": "2025-12",
        "price": 890.43
      },
      {
        "date": "2026-01",
        "price": 848.08
      },
      {
        "date": "2026-02",
        "price": 915.57
      },
      {
        "date": "2026-03",
        "price": 751.2
      }
    ],
    "Aluminum Sheets": [
      {
        "date": "2023-04",
        "price": 2507.31
      },
      {
        "date": "2023-05",
        "price": 2599.05
      },
      {
        "date": "2023-06",
        "price": 2570.74
      },
      {
        "date": "2023-07",
        "price": 3093.76
      },
      {
        "date": "2023-08",
        "price": 2598.15
      },
      {
        "date": "2023-09",
        "price": 2580.78
      },
      {
        "date": "2023-10",
        "price": 2575.03
      },
      {
        "date": "2023-11",
        "price": 2933.43
      },
      {
        "date": "2023-12",
        "price": 3122.53
      },
      {
        "date": "2024-01",
        "price": 3067.42
      },
      {
        "date": "2024-02",
        "price": 3161.53
      },
      {
        "date": "2024-03",
        "price": 3148.06
      },
      {
        "date": "2024-04",
        "price": 4115.22
      },
      {
        "date": "2024-05",
        "price": 3142.67
      },
      {
        "date": "2024-06",
        "price": 3045.67
      },
      {
        "date": "2024-07",
        "price": 2805.28
      },
      {
        "date": "2024-08",
        "price": 2811.02
      },
      {
        "date": "2024-09",
        "price": 2256.83
      },
      {
        "date": "2024-10",
        "price": 2412.25
      },
      {
        "date": "2024-11",
        "price": 2908.64
      },
      {
        "date": "2024-12",
        "price": 3014.65
      },
      {
        "date": "2025-01",
        "price": 3005.83
      },
      {
        "date": "2025-02",
        "price": 3403.13
      },
      {
        "date": "2025-03",
        "price": 3106.83
      },
      {
        "date": "2025-04",
        "price": 3022.48
      },
      {
        "date": "2025-05",
        "price": 3039.06
      },
      {
        "date": "2025-06",
        "price": 2824.37
      },
      {
        "date": "2025-07",
        "price": 2329.24
      },
      {
        "date": "2025-08",
        "price": 2694.25
      },
      {
        "date": "2025-09",
        "price": 2741.79
      },
      {
        "date": "2025-10",
        "price": 2710.0
      },
      {
        "date": "2025-11",
        "price": 4158.39
      },
      {
        "date": "2025-12",
        "price": 3604.72
      },
      {
        "date": "2026-01",
        "price": 3353.67
      },
      {
        "date": "2026-02",
        "price": 3433.1
      },
      {
        "date": "2026-03",
        "price": 2835.13
      }
    ],
    "Copper Wire": [
      {
        "date": "2023-04",
        "price": 8880.06
      },
      {
        "date": "2023-05",
        "price": 9500.19
      },
      {
        "date": "2023-06",
        "price": 10102.49
      },
      {
        "date": "2023-07",
        "price": 12305.95
      },
      {
        "date": "2023-08",
        "price": 9677.09
      },
      {
        "date": "2023-09",
        "price": 9712.51
      },
      {
        "date": "2023-10",
        "price": 8807.27
      },
      {
        "date": "2023-11",
        "price": 11109.26
      },
      {
        "date": "2023-12",
        "price": 10858.92
      },
      {
        "date": "2024-01",
        "price": 10596.67
      },
      {
        "date": "2024-02",
        "price": 11306.46
      },
      {
        "date": "2024-03",
        "price": 11622.08
      },
      {
        "date": "2024-04",
        "price": 15221.6
      },
      {
        "date": "2024-05",
        "price": 10054.71
      },
      {
        "date": "2024-06",
        "price": 10686.66
      },
      {
        "date": "2024-07",
        "price": 9792.51
      },
      {
        "date": "2024-08",
        "price": 9601.72
      },
      {
        "date": "2024-09",
        "price": 7996.34
      },
      {
        "date": "2024-10",
        "price": 8732.01
      },
      {
        "date": "2024-11",
        "price": 8699.43
      },
      {
        "date": "2024-12",
        "price": 9040.17
      },
      {
        "date": "2025-01",
        "price": 9249.0
      },
      {
        "date": "2025-02",
        "price": 12354.04
      },
      {
        "date": "2025-03",
        "price": 11149.67
      },
      {
        "date": "2025-04",
        "price": 11007.76
      },
      {
        "date": "2025-05",
        "price": 10182.52
      },
      {
        "date": "2025-06",
        "price": 10159.25
      },
      {
        "date": "2025-07",
        "price": 6887.72
      },
      {
        "date": "2025-08",
        "price": 8454.16
      },
      {
        "date": "2025-09",
        "price": 8917.74
      },
      {
        "date": "2025-10",
        "price": 7967.51
      },
      {
        "date": "2025-11",
        "price": 12976.74
      },
      {
        "date": "2025-12",
        "price": 10390.52
      },
      {
        "date": "2026-01",
        "price": 11103.18
      },
      {
        "date": "2026-02",
        "price": 10831.67
      },
      {
        "date": "2026-03",
        "price": 7970.88
      }
    ],
    "Plastic Pellets": [
      {
        "date": "2023-04",
        "price": 1253.65
      },
      {
        "date": "2023-05",
        "price": 1198.1
      },
      {
        "date": "2023-06",
        "price": 1252.18
      },
      {
        "date": "2023-07",
        "price": 1405.81
      },
      {
        "date": "2023-08",
        "price": 1285.5
      },
      {
        "date": "2023-09",
        "price": 1176.16
      },
      {
        "date": "2023-10",
        "price": 1118.29
      },
      {
        "date": "2023-11",
        "price": 1219.11
      },
      {
        "date": "2023-12",
        "price": 1171.36
      },
      {
        "date": "2024-01",
        "price": 1173.79
      },
      {
        "date": "2024-02",
        "price": 1105.87
      },
      {
        "date": "2024-03",
        "price": 1125.83
      },
      {
        "date": "2024-04",
        "price": 1352.6
      },
      {
        "date": "2024-05",
        "price": 1202.3
      },
      {
        "date": "2024-06",
        "price": 1385.87
      },
      {
        "date": "2024-07",
        "price": 1384.21
      },
      {
        "date": "2024-08",
        "price": 1111.16
      },
      {
        "date": "2024-09",
        "price": 919.64
      },
      {
        "date": "2024-10",
        "price": 903.55
      },
      {
        "date": "2024-11",
        "price": 889.02
      },
      {
        "date": "2024-12",
        "price": 912.86
      },
      {
        "date": "2025-01",
        "price": 911.84
      },
      {
        "date": "2025-02",
        "price": 1150.67
      },
      {
        "date": "2025-03",
        "price": 1180.96
      },
      {
        "date": "2025-04",
        "price": 1178.21
      },
      {
        "date": "2025-05",
        "price": 1177.13
      },
      {
        "date": "2025-06",
        "price": 1133.36
      },
      {
        "date": "2025-07",
        "price": 829.71
      },
      {
        "date": "2025-08",
        "price": 879.47
      },
      {
        "date": "2025-09",
        "price": 910.87
      },
      {
        "date": "2025-10",
        "price": 923.68
      },
      {
        "date": "2025-11",
        "price": 1364.17
      },
      {
        "date": "2025-12",
        "price": 1304.16
      },
      {
        "date": "2026-01",
        "price": 1369.46
      },
      {
        "date": "2026-02",
        "price": 1391.46
      },
      {
        "date": "2026-03",
        "price": 1051.82
      }
    ],
    "Carbon Fiber": [
      {
        "date": "2023-04",
        "price": 22983.67
      },
      {
        "date": "2023-05",
        "price": 23706.29
      },
      {
        "date": "2023-06",
        "price": 21714.38
      },
      {
        "date": "2023-07",
        "price": 23909.43
      },
      {
        "date": "2023-08",
        "price": 23088.17
      },
      {
        "date": "2023-09",
        "price": 22378.35
      },
      {
        "date": "2023-10",
        "price": 22045.75
      },
      {
        "date": "2023-11",
        "price": 22870.96
      },
      {
        "date": "2023-12",
        "price": 20595.84
      },
      {
        "date": "2024-01",
        "price": 21546.84
      },
      {
        "date": "2024-02",
        "price": 23586.51
      },
      {
        "date": "2024-03",
        "price": 24994.96
      },
      {
        "date": "2024-04",
        "price": 26020.79
      },
      {
        "date": "2024-05",
        "price": 22771.11
      },
      {
        "date": "2024-06",
        "price": 22508.17
      },
      {
        "date": "2024-07",
        "price": 19925.29
      },
      {
        "date": "2024-08",
        "price": 17668.82
      },
      {
        "date": "2024-09",
        "price": 16495.01
      },
      {
        "date": "2024-10",
        "price": 15826.71
      },
      {
        "date": "2024-11",
        "price": 17744.2
      },
      {
        "date": "2024-12",
        "price": 19576.5
      },
      {
        "date": "2025-01",
        "price": 18271.68
      },
      {
        "date": "2025-02",
        "price": 22909.91
      },
      {
        "date": "2025-03",
        "price": 23542.52
      },
      {
        "date": "2025-04",
        "price": 21137.42
      },
      {
        "date": "2025-05",
        "price": 22429.97
      },
      {
        "date": "2025-06",
        "price": 22999.36
      },
      {
        "date": "2025-07",
        "price": 21146.41
      },
      {
        "date": "2025-08",
        "price": 21319.3
      },
      {
        "date": "2025-09",
        "price": 21976.95
      },
      {
        "date": "2025-10",
        "price": 23236.62
      },
      {
        "date": "2025-11",
        "price": 30910.48
      },
      {
        "date": "2025-12",
        "price": 33354.05
      },
      {
        "date": "2026-01",
        "price": 33461.9
      },
      {
        "date": "2026-02",
        "price": 30556.63
      },
      {
        "date": "2026-03",
        "price": 28162.46
      }
    ],
    "Silicon Wafers": [
      {
        "date": "2023-04",
        "price": 15670.69
      },
      {
        "date": "2023-05",
        "price": 16103.05
      },
      {
        "date": "2023-06",
        "price": 17043.41
      },
      {
        "date": "2023-07",
        "price": 22556.63
      },
      {
        "date": "2023-08",
        "price": 16720.17
      },
      {
        "date": "2023-09",
        "price": 18985.25
      },
      {
        "date": "2023-10",
        "price": 17056.5
      },
      {
        "date": "2023-11",
        "price": 19761.47
      },
      {
        "date": "2023-12",
        "price": 17233.58
      },
      {
        "date": "2024-01",
        "price": 17165.34
      },
      {
        "date": "2024-02",
        "price": 16582.48
      },
      {
        "date": "2024-03",
        "price": 17537.79
      },
      {
        "date": "2024-04",
        "price": 23031.17
      },
      {
        "date": "2024-05",
        "price": 17493.95
      },
      {
        "date": "2024-06",
        "price": 16616.85
      },
      {
        "date": "2024-07",
        "price": 16367.63
      },
      {
        "date": "2024-08",
        "price": 16432.38
      },
      {
        "date": "2024-09",
        "price": 14835.06
      },
      {
        "date": "2024-10",
        "price": 16632.01
      },
      {
        "date": "2024-11",
        "price": 17113.28
      },
      {
        "date": "2024-12",
        "price": 20273.29
      },
      {
        "date": "2025-01",
        "price": 19905.26
      },
      {
        "date": "2025-02",
        "price": 26589.94
      },
      {
        "date": "2025-03",
        "price": 22522.71
      },
      {
        "date": "2025-04",
        "price": 19977.07
      },
      {
        "date": "2025-05",
        "price": 21003.29
      },
      {
        "date": "2025-06",
        "price": 21549.72
      },
      {
        "date": "2025-07",
        "price": 15653.18
      },
      {
        "date": "2025-08",
        "price": 17929.67
      },
      {
        "date": "2025-09",
        "price": 18393.09
      },
      {
        "date": "2025-10",
        "price": 16316.98
      },
      {
        "date": "2025-11",
        "price": 23757.25
      },
      {
        "date": "2025-12",
        "price": 18613.74
      },
      {
        "date": "2026-01",
        "price": 18534.25
      },
      {
        "date": "2026-02",
        "price": 18835.66
      },
      {
        "date": "2026-03",
        "price": 13904.0
      }
    ],
    "Titanium Alloy": [
      {
        "date": "2023-04",
        "price": 36564.94
      },
      {
        "date": "2023-05",
        "price": 37228.69
      },
      {
        "date": "2023-06",
        "price": 38990.5
      },
      {
        "date": "2023-07",
        "price": 39989.37
      },
      {
        "date": "2023-08",
        "price": 34037.62
      },
      {
        "date": "2023-09",
        "price": 36251.2
      },
      {
        "date": "2023-10",
        "price": 31140.72
      },
      {
        "date": "2023-11",
        "price": 36948.29
      },
      {
        "date": "2023-12",
        "price": 36113.74
      },
      {
        "date": "2024-01",
        "price": 36437.45
      },
      {
        "date": "2024-02",
        "price": 32547.42
      },
      {
        "date": "2024-03",
        "price": 34727.35
      },
      {
        "date": "2024-04",
        "price": 42368.09
      },
      {
        "date": "2024-05",
        "price": 35238.86
      },
      {
        "date": "2024-06",
        "price": 34193.79
      },
      {
        "date": "2024-07",
        "price": 32245.28
      },
      {
        "date": "2024-08",
        "price": 29984.18
      },
      {
        "date": "2024-09",
        "price": 26077.96
      },
      {
        "date": "2024-10",
        "price": 27059.85
      },
      {
        "date": "2024-11",
        "price": 28905.96
      },
      {
        "date": "2024-12",
        "price": 29996.44
      },
      {
        "date": "2025-01",
        "price": 28401.19
      },
      {
        "date": "2025-02",
        "price": 36967.14
      },
      {
        "date": "2025-03",
        "price": 34214.62
      },
      {
        "date": "2025-04",
        "price": 39027.07
      },
      {
        "date": "2025-05",
        "price": 37573.82
      },
      {
        "date": "2025-06",
        "price": 36695.8
      },
      {
        "date": "2025-07",
        "price": 28596.28
      },
      {
        "date": "2025-08",
        "price": 29897.5
      },
      {
        "date": "2025-09",
        "price": 29250.11
      },
      {
        "date": "2025-10",
        "price": 30843.15
      },
      {
        "date": "2025-11",
        "price": 41650.62
      },
      {
        "date": "2025-12",
        "price": 42436.93
      },
      {
        "date": "2026-01",
        "price": 40637.0
      },
      {
        "date": "2026-02",
        "price": 39912.67
      },
      {
        "date": "2026-03",
        "price": 28778.93
      }
    ],
    "Nickel Powder": [
      {
        "date": "2023-04",
        "price": 18804.82
      },
      {
        "date": "2023-05",
        "price": 17763.84
      },
      {
        "date": "2023-06",
        "price": 18172.69
      },
      {
        "date": "2023-07",
        "price": 20906.19
      },
      {
        "date": "2023-08",
        "price": 15579.47
      },
      {
        "date": "2023-09",
        "price": 16596.16
      },
      {
        "date": "2023-10",
        "price": 16251.32
      },
      {
        "date": "2023-11",
        "price": 21051.72
      },
      {
        "date": "2023-12",
        "price": 19330.77
      },
      {
        "date": "2024-01",
        "price": 16276.42
      },
      {
        "date": "2024-02",
        "price": 19617.11
      },
      {
        "date": "2024-03",
        "price": 20088.75
      },
      {
        "date": "2024-04",
        "price": 24664.8
      },
      {
        "date": "2024-05",
        "price": 18738.6
      },
      {
        "date": "2024-06",
        "price": 20811.95
      },
      {
        "date": "2024-07",
        "price": 19446.84
      },
      {
        "date": "2024-08",
        "price": 18207.29
      },
      {
        "date": "2024-09",
        "price": 13779.29
      },
      {
        "date": "2024-10",
        "price": 15618.08
      },
      {
        "date": "2024-11",
        "price": 15956.96
      },
      {
        "date": "2024-12",
        "price": 16952.89
      },
      {
        "date": "2025-01",
        "price": 16570.2
      },
      {
        "date": "2025-02",
        "price": 23037.4
      },
      {
        "date": "2025-03",
        "price": 17017.67
      },
      {
        "date": "2025-04",
        "price": 16708.84
      },
      {
        "date": "2025-05",
        "price": 15828.65
      },
      {
        "date": "2025-06",
        "price": 17229.88
      },
      {
        "date": "2025-07",
        "price": 10962.03
      },
      {
        "date": "2025-08",
        "price": 12760.72
      },
      {
        "date": "2025-09",
        "price": 12646.62
      },
      {
        "date": "2025-10",
        "price": 14512.27
      },
      {
        "date": "2025-11",
        "price": 22389.76
      },
      {
        "date": "2025-12",
        "price": 19341.2
      },
      {
        "date": "2026-01",
        "price": 21080.09
      },
      {
        "date": "2026-02",
        "price": 21782.54
      },
      {
        "date": "2026-03",
        "price": 15521.49
      }
    ],
    "Graphite Electrodes": [
      {
        "date": "2023-04",
        "price": 4701.21
      },
      {
        "date": "2023-05",
        "price": 4858.71
      },
      {
        "date": "2023-06",
        "price": 5149.09
      },
      {
        "date": "2023-07",
        "price": 6244.85
      },
      {
        "date": "2023-08",
        "price": 5188.13
      },
      {
        "date": "2023-09",
        "price": 5792.37
      },
      {
        "date": "2023-10",
        "price": 5387.42
      },
      {
        "date": "2023-11",
        "price": 6491.5
      },
      {
        "date": "2023-12",
        "price": 6339.63
      },
      {
        "date": "2024-01",
        "price": 6126.45
      },
      {
        "date": "2024-02",
        "price": 6368.86
      },
      {
        "date": "2024-03",
        "price": 7004.59
      },
      {
        "date": "2024-04",
        "price": 7941.1
      },
      {
        "date": "2024-05",
        "price": 6358.66
      },
      {
        "date": "2024-06",
        "price": 6126.95
      },
      {
        "date": "2024-07",
        "price": 5648.45
      },
      {
        "date": "2024-08",
        "price": 5471.05
      },
      {
        "date": "2024-09",
        "price": 4321.91
      },
      {
        "date": "2024-10",
        "price": 4727.33
      },
      {
        "date": "2024-11",
        "price": 4562.58
      },
      {
        "date": "2024-12",
        "price": 5377.92
      },
      {
        "date": "2025-01",
        "price": 5289.44
      },
      {
        "date": "2025-02",
        "price": 7244.1
      },
      {
        "date": "2025-03",
        "price": 6107.56
      },
      {
        "date": "2025-04",
        "price": 5980.52
      },
      {
        "date": "2025-05",
        "price": 5992.78
      },
      {
        "date": "2025-06",
        "price": 6413.87
      },
      {
        "date": "2025-07",
        "price": 4555.11
      },
      {
        "date": "2025-08",
        "price": 5532.1
      },
      {
        "date": "2025-09",
        "price": 5194.26
      },
      {
        "date": "2025-10",
        "price": 4819.55
      },
      {
        "date": "2025-11",
        "price": 7083.26
      },
      {
        "date": "2025-12",
        "price": 5716.43
      },
      {
        "date": "2026-01",
        "price": 5783.46
      },
      {
        "date": "2026-02",
        "price": 5403.37
      },
      {
        "date": "2026-03",
        "price": 4162.82
      }
    ],
    "Rare Earth Magnets": [
      {
        "date": "2023-04",
        "price": 88800.56
      },
      {
        "date": "2023-05",
        "price": 87974.58
      },
      {
        "date": "2023-06",
        "price": 87013.67
      },
      {
        "date": "2023-07",
        "price": 108666.92
      },
      {
        "date": "2023-08",
        "price": 77603.47
      },
      {
        "date": "2023-09",
        "price": 83596.07
      },
      {
        "date": "2023-10",
        "price": 77061.56
      },
      {
        "date": "2023-11",
        "price": 95160.31
      },
      {
        "date": "2023-12",
        "price": 83951.98
      },
      {
        "date": "2024-01",
        "price": 88029.22
      },
      {
        "date": "2024-02",
        "price": 82215.77
      },
      {
        "date": "2024-03",
        "price": 89200.15
      },
      {
        "date": "2024-04",
        "price": 111666.12
      },
      {
        "date": "2024-05",
        "price": 84605.88
      },
      {
        "date": "2024-06",
        "price": 99191.34
      },
      {
        "date": "2024-07",
        "price": 93392.5
      },
      {
        "date": "2024-08",
        "price": 93137.42
      },
      {
        "date": "2024-09",
        "price": 81500.26
      },
      {
        "date": "2024-10",
        "price": 84695.99
      },
      {
        "date": "2024-11",
        "price": 86692.8
      },
      {
        "date": "2024-12",
        "price": 81023.74
      },
      {
        "date": "2025-01",
        "price": 82389.64
      },
      {
        "date": "2025-02",
        "price": 125445.71
      },
      {
        "date": "2025-03",
        "price": 110145.58
      },
      {
        "date": "2025-04",
        "price": 108055.77
      },
      {
        "date": "2025-05",
        "price": 103441.33
      },
      {
        "date": "2025-06",
        "price": 106087.29
      },
      {
        "date": "2025-07",
        "price": 75440.81
      },
      {
        "date": "2025-08",
        "price": 87902.06
      },
      {
        "date": "2025-09",
        "price": 88380.14
      },
      {
        "date": "2025-10",
        "price": 86114.84
      },
      {
        "date": "2025-11",
        "price": 141752.93
      },
      {
        "date": "2025-12",
        "price": 108816.42
      },
      {
        "date": "2026-01",
        "price": 96595.52
      },
      {
        "date": "2026-02",
        "price": 98491.65
      },
      {
        "date": "2026-03",
        "price": 67546.91
      }
    ]
  },
  "demand_history": {
    "Steel Coils": [
      {
        "date": "2023-04",
        "demand": 732
      },
      {
        "date": "2023-05",
        "demand": 771
      },
      {
        "date": "2023-06",
        "demand": 647
      },
      {
        "date": "2023-07",
        "demand": 559
      },
      {
        "date": "2023-08",
        "demand": 422
      },
      {
        "date": "2023-09",
        "demand": 211
      },
      {
        "date": "2023-10",
        "demand": 205
      },
      {
        "date": "2023-11",
        "demand": 174
      },
      {
        "date": "2023-12",
        "demand": 117
      },
      {
        "date": "2024-01",
        "demand": 180
      },
      {
        "date": "2024-02",
        "demand": 157
      },
      {
        "date": "2024-03",
        "demand": 46
      },
      {
        "date": "2024-04",
        "demand": 38
      },
      {
        "date": "2024-05",
        "demand": 65
      },
      {
        "date": "2024-06",
        "demand": 20
      },
      {
        "date": "2024-07",
        "demand": 20
      },
      {
        "date": "2024-08",
        "demand": 146
      },
      {
        "date": "2024-09",
        "demand": 192
      },
      {
        "date": "2024-10",
        "demand": 132
      },
      {
        "date": "2024-11",
        "demand": 20
      },
      {
        "date": "2024-12",
        "demand": 81
      },
      {
        "date": "2025-01",
        "demand": 20
      },
      {
        "date": "2025-02",
        "demand": 48
      },
      {
        "date": "2025-03",
        "demand": 24
      },
      {
        "date": "2025-04",
        "demand": 171
      },
      {
        "date": "2025-05",
        "demand": 108
      },
      {
        "date": "2025-06",
        "demand": 145
      },
      {
        "date": "2025-07",
        "demand": 143
      },
      {
        "date": "2025-08",
        "demand": 216
      },
      {
        "date": "2025-09",
        "demand": 298
      },
      {
        "date": "2025-10",
        "demand": 287
      },
      {
        "date": "2025-11",
        "demand": 250
      },
      {
        "date": "2025-12",
        "demand": 324
      },
      {
        "date": "2026-01",
        "demand": 281
      },
      {
        "date": "2026-02",
        "demand": 263
      },
      {
        "date": "2026-03",
        "demand": 252
      }
    ],
    "Aluminum Sheets": [
      {
        "date": "2023-04",
        "demand": 612
      },
      {
        "date": "2023-05",
        "demand": 410
      },
      {
        "date": "2023-06",
        "demand": 444
      },
      {
        "date": "2023-07",
        "demand": 463
      },
      {
        "date": "2023-08",
        "demand": 464
      },
      {
        "date": "2023-09",
        "demand": 390
      },
      {
        "date": "2023-10",
        "demand": 264
      },
      {
        "date": "2023-11",
        "demand": 241
      },
      {
        "date": "2023-12",
        "demand": 221
      },
      {
        "date": "2024-01",
        "demand": 213
      },
      {
        "date": "2024-02",
        "demand": 235
      },
      {
        "date": "2024-03",
        "demand": 138
      },
      {
        "date": "2024-04",
        "demand": 168
      },
      {
        "date": "2024-05",
        "demand": 142
      },
      {
        "date": "2024-06",
        "demand": 134
      },
      {
        "date": "2024-07",
        "demand": 104
      },
      {
        "date": "2024-08",
        "demand": 104
      },
      {
        "date": "2024-09",
        "demand": 104
      },
      {
        "date": "2024-10",
        "demand": 72
      },
      {
        "date": "2024-11",
        "demand": 57
      },
      {
        "date": "2024-12",
        "demand": 40
      },
      {
        "date": "2025-01",
        "demand": 20
      },
      {
        "date": "2025-02",
        "demand": 20
      },
      {
        "date": "2025-03",
        "demand": 20
      },
      {
        "date": "2025-04",
        "demand": 20
      },
      {
        "date": "2025-05",
        "demand": 43
      },
      {
        "date": "2025-06",
        "demand": 20
      },
      {
        "date": "2025-07",
        "demand": 20
      },
      {
        "date": "2025-08",
        "demand": 94
      },
      {
        "date": "2025-09",
        "demand": 36
      },
      {
        "date": "2025-10",
        "demand": 20
      },
      {
        "date": "2025-11",
        "demand": 20
      },
      {
        "date": "2025-12",
        "demand": 20
      },
      {
        "date": "2026-01",
        "demand": 20
      },
      {
        "date": "2026-02",
        "demand": 20
      },
      {
        "date": "2026-03",
        "demand": 20
      }
    ],
    "Copper Wire": [
      {
        "date": "2023-04",
        "demand": 500
      },
      {
        "date": "2023-05",
        "demand": 514
      },
      {
        "date": "2023-06",
        "demand": 443
      },
      {
        "date": "2023-07",
        "demand": 484
      },
      {
        "date": "2023-08",
        "demand": 417
      },
      {
        "date": "2023-09",
        "demand": 326
      },
      {
        "date": "2023-10",
        "demand": 344
      },
      {
        "date": "2023-11",
        "demand": 260
      },
      {
        "date": "2023-12",
        "demand": 215
      },
      {
        "date": "2024-01",
        "demand": 181
      },
      {
        "date": "2024-02",
        "demand": 244
      },
      {
        "date": "2024-03",
        "demand": 229
      },
      {
        "date": "2024-04",
        "demand": 241
      },
      {
        "date": "2024-05",
        "demand": 263
      },
      {
        "date": "2024-06",
        "demand": 254
      },
      {
        "date": "2024-07",
        "demand": 332
      },
      {
        "date": "2024-08",
        "demand": 317
      },
      {
        "date": "2024-09",
        "demand": 267
      },
      {
        "date": "2024-10",
        "demand": 292
      },
      {
        "date": "2024-11",
        "demand": 279
      },
      {
        "date": "2024-12",
        "demand": 204
      },
      {
        "date": "2025-01",
        "demand": 175
      },
      {
        "date": "2025-02",
        "demand": 179
      },
      {
        "date": "2025-03",
        "demand": 355
      },
      {
        "date": "2025-04",
        "demand": 322
      },
      {
        "date": "2025-05",
        "demand": 320
      },
      {
        "date": "2025-06",
        "demand": 367
      },
      {
        "date": "2025-07",
        "demand": 381
      },
      {
        "date": "2025-08",
        "demand": 375
      },
      {
        "date": "2025-09",
        "demand": 361
      },
      {
        "date": "2025-10",
        "demand": 260
      },
      {
        "date": "2025-11",
        "demand": 409
      },
      {
        "date": "2025-12",
        "demand": 274
      },
      {
        "date": "2026-01",
        "demand": 223
      },
      {
        "date": "2026-02",
        "demand": 146
      },
      {
        "date": "2026-03",
        "demand": 113
      }
    ],
    "Plastic Pellets": [
      {
        "date": "2023-04",
        "demand": 1163
      },
      {
        "date": "2023-05",
        "demand": 1262
      },
      {
        "date": "2023-06",
        "demand": 1269
      },
      {
        "date": "2023-07",
        "demand": 1379
      },
      {
        "date": "2023-08",
        "demand": 1230
      },
      {
        "date": "2023-09",
        "demand": 1212
      },
      {
        "date": "2023-10",
        "demand": 1049
      },
      {
        "date": "2023-11",
        "demand": 890
      },
      {
        "date": "2023-12",
        "demand": 808
      },
      {
        "date": "2024-01",
        "demand": 785
      },
      {
        "date": "2024-02",
        "demand": 690
      },
      {
        "date": "2024-03",
        "demand": 704
      },
      {
        "date": "2024-04",
        "demand": 804
      },
      {
        "date": "2024-05",
        "demand": 902
      },
      {
        "date": "2024-06",
        "demand": 913
      },
      {
        "date": "2024-07",
        "demand": 1056
      },
      {
        "date": "2024-08",
        "demand": 968
      },
      {
        "date": "2024-09",
        "demand": 1257
      },
      {
        "date": "2024-10",
        "demand": 1052
      },
      {
        "date": "2024-11",
        "demand": 954
      },
      {
        "date": "2024-12",
        "demand": 729
      },
      {
        "date": "2025-01",
        "demand": 690
      },
      {
        "date": "2025-02",
        "demand": 678
      },
      {
        "date": "2025-03",
        "demand": 479
      },
      {
        "date": "2025-04",
        "demand": 455
      },
      {
        "date": "2025-05",
        "demand": 520
      },
      {
        "date": "2025-06",
        "demand": 258
      },
      {
        "date": "2025-07",
        "demand": 457
      },
      {
        "date": "2025-08",
        "demand": 462
      },
      {
        "date": "2025-09",
        "demand": 284
      },
      {
        "date": "2025-10",
        "demand": 136
      },
      {
        "date": "2025-11",
        "demand": 155
      },
      {
        "date": "2025-12",
        "demand": 76
      },
      {
        "date": "2026-01",
        "demand": 54
      },
      {
        "date": "2026-02",
        "demand": 208
      },
      {
        "date": "2026-03",
        "demand": 273
      }
    ],
    "Carbon Fiber": [
      {
        "date": "2023-04",
        "demand": 158
      },
      {
        "date": "2023-05",
        "demand": 140
      },
      {
        "date": "2023-06",
        "demand": 93
      },
      {
        "date": "2023-07",
        "demand": 91
      },
      {
        "date": "2023-08",
        "demand": 59
      },
      {
        "date": "2023-09",
        "demand": 43
      },
      {
        "date": "2023-10",
        "demand": 28
      },
      {
        "date": "2023-11",
        "demand": 22
      },
      {
        "date": "2023-12",
        "demand": 20
      },
      {
        "date": "2024-01",
        "demand": 27
      },
      {
        "date": "2024-02",
        "demand": 20
      },
      {
        "date": "2024-03",
        "demand": 27
      },
      {
        "date": "2024-04",
        "demand": 20
      },
      {
        "date": "2024-05",
        "demand": 23
      },
      {
        "date": "2024-06",
        "demand": 20
      },
      {
        "date": "2024-07",
        "demand": 20
      },
      {
        "date": "2024-08",
        "demand": 21
      },
      {
        "date": "2024-09",
        "demand": 20
      },
      {
        "date": "2024-10",
        "demand": 20
      },
      {
        "date": "2024-11",
        "demand": 20
      },
      {
        "date": "2024-12",
        "demand": 21
      },
      {
        "date": "2025-01",
        "demand": 20
      },
      {
        "date": "2025-02",
        "demand": 20
      },
      {
        "date": "2025-03",
        "demand": 29
      },
      {
        "date": "2025-04",
        "demand": 20
      },
      {
        "date": "2025-05",
        "demand": 20
      },
      {
        "date": "2025-06",
        "demand": 31
      },
      {
        "date": "2025-07",
        "demand": 27
      },
      {
        "date": "2025-08",
        "demand": 24
      },
      {
        "date": "2025-09",
        "demand": 20
      },
      {
        "date": "2025-10",
        "demand": 20
      },
      {
        "date": "2025-11",
        "demand": 20
      },
      {
        "date": "2025-12",
        "demand": 20
      },
      {
        "date": "2026-01",
        "demand": 20
      },
      {
        "date": "2026-02",
        "demand": 20
      },
      {
        "date": "2026-03",
        "demand": 20
      }
    ],
    "Silicon Wafers": [
      {
        "date": "2023-04",
        "demand": 283
      },
      {
        "date": "2023-05",
        "demand": 261
      },
      {
        "date": "2023-06",
        "demand": 365
      },
      {
        "date": "2023-07",
        "demand": 284
      },
      {
        "date": "2023-08",
        "demand": 252
      },
      {
        "date": "2023-09",
        "demand": 122
      },
      {
        "date": "2023-10",
        "demand": 87
      },
      {
        "date": "2023-11",
        "demand": 58
      },
      {
        "date": "2023-12",
        "demand": 57
      },
      {
        "date": "2024-01",
        "demand": 20
      },
      {
        "date": "2024-02",
        "demand": 43
      },
      {
        "date": "2024-03",
        "demand": 60
      },
      {
        "date": "2024-04",
        "demand": 74
      },
      {
        "date": "2024-05",
        "demand": 62
      },
      {
        "date": "2024-06",
        "demand": 55
      },
      {
        "date": "2024-07",
        "demand": 46
      },
      {
        "date": "2024-08",
        "demand": 67
      },
      {
        "date": "2024-09",
        "demand": 82
      },
      {
        "date": "2024-10",
        "demand": 154
      },
      {
        "date": "2024-11",
        "demand": 111
      },
      {
        "date": "2024-12",
        "demand": 117
      },
      {
        "date": "2025-01",
        "demand": 109
      },
      {
        "date": "2025-02",
        "demand": 97
      },
      {
        "date": "2025-03",
        "demand": 76
      },
      {
        "date": "2025-04",
        "demand": 61
      },
      {
        "date": "2025-05",
        "demand": 67
      },
      {
        "date": "2025-06",
        "demand": 39
      },
      {
        "date": "2025-07",
        "demand": 68
      },
      {
        "date": "2025-08",
        "demand": 109
      },
      {
        "date": "2025-09",
        "demand": 65
      },
      {
        "date": "2025-10",
        "demand": 47
      },
      {
        "date": "2025-11",
        "demand": 24
      },
      {
        "date": "2025-12",
        "demand": 26
      },
      {
        "date": "2026-01",
        "demand": 29
      },
      {
        "date": "2026-02",
        "demand": 62
      },
      {
        "date": "2026-03",
        "demand": 80
      }
    ],
    "Titanium Alloy": [
      {
        "date": "2023-04",
        "demand": 91
      },
      {
        "date": "2023-05",
        "demand": 84
      },
      {
        "date": "2023-06",
        "demand": 82
      },
      {
        "date": "2023-07",
        "demand": 80
      },
      {
        "date": "2023-08",
        "demand": 72
      },
      {
        "date": "2023-09",
        "demand": 54
      },
      {
        "date": "2023-10",
        "demand": 41
      },
      {
        "date": "2023-11",
        "demand": 20
      },
      {
        "date": "2023-12",
        "demand": 20
      },
      {
        "date": "2024-01",
        "demand": 20
      },
      {
        "date": "2024-02",
        "demand": 20
      },
      {
        "date": "2024-03",
        "demand": 20
      },
      {
        "date": "2024-04",
        "demand": 20
      },
      {
        "date": "2024-05",
        "demand": 21
      },
      {
        "date": "2024-06",
        "demand": 20
      },
      {
        "date": "2024-07",
        "demand": 20
      },
      {
        "date": "2024-08",
        "demand": 27
      },
      {
        "date": "2024-09",
        "demand": 21
      },
      {
        "date": "2024-10",
        "demand": 20
      },
      {
        "date": "2024-11",
        "demand": 20
      },
      {
        "date": "2024-12",
        "demand": 20
      },
      {
        "date": "2025-01",
        "demand": 20
      },
      {
        "date": "2025-02",
        "demand": 22
      },
      {
        "date": "2025-03",
        "demand": 26
      },
      {
        "date": "2025-04",
        "demand": 24
      },
      {
        "date": "2025-05",
        "demand": 35
      },
      {
        "date": "2025-06",
        "demand": 39
      },
      {
        "date": "2025-07",
        "demand": 52
      },
      {
        "date": "2025-08",
        "demand": 53
      },
      {
        "date": "2025-09",
        "demand": 50
      },
      {
        "date": "2025-10",
        "demand": 44
      },
      {
        "date": "2025-11",
        "demand": 53
      },
      {
        "date": "2025-12",
        "demand": 47
      },
      {
        "date": "2026-01",
        "demand": 36
      },
      {
        "date": "2026-02",
        "demand": 30
      },
      {
        "date": "2026-03",
        "demand": 22
      }
    ],
    "Nickel Powder": [
      {
        "date": "2023-04",
        "demand": 225
      },
      {
        "date": "2023-05",
        "demand": 261
      },
      {
        "date": "2023-06",
        "demand": 240
      },
      {
        "date": "2023-07",
        "demand": 228
      },
      {
        "date": "2023-08",
        "demand": 224
      },
      {
        "date": "2023-09",
        "demand": 200
      },
      {
        "date": "2023-10",
        "demand": 189
      },
      {
        "date": "2023-11",
        "demand": 177
      },
      {
        "date": "2023-12",
        "demand": 143
      },
      {
        "date": "2024-01",
        "demand": 99
      },
      {
        "date": "2024-02",
        "demand": 108
      },
      {
        "date": "2024-03",
        "demand": 74
      },
      {
        "date": "2024-04",
        "demand": 71
      },
      {
        "date": "2024-05",
        "demand": 71
      },
      {
        "date": "2024-06",
        "demand": 58
      },
      {
        "date": "2024-07",
        "demand": 40
      },
      {
        "date": "2024-08",
        "demand": 20
      },
      {
        "date": "2024-09",
        "demand": 20
      },
      {
        "date": "2024-10",
        "demand": 20
      },
      {
        "date": "2024-11",
        "demand": 20
      },
      {
        "date": "2024-12",
        "demand": 20
      },
      {
        "date": "2025-01",
        "demand": 20
      },
      {
        "date": "2025-02",
        "demand": 20
      },
      {
        "date": "2025-03",
        "demand": 20
      },
      {
        "date": "2025-04",
        "demand": 20
      },
      {
        "date": "2025-05",
        "demand": 20
      },
      {
        "date": "2025-06",
        "demand": 33
      },
      {
        "date": "2025-07",
        "demand": 32
      },
      {
        "date": "2025-08",
        "demand": 37
      },
      {
        "date": "2025-09",
        "demand": 31
      },
      {
        "date": "2025-10",
        "demand": 20
      },
      {
        "date": "2025-11",
        "demand": 20
      },
      {
        "date": "2025-12",
        "demand": 20
      },
      {
        "date": "2026-01",
        "demand": 20
      },
      {
        "date": "2026-02",
        "demand": 24
      },
      {
        "date": "2026-03",
        "demand": 28
      }
    ],
    "Graphite Electrodes": [
      {
        "date": "2023-04",
        "demand": 334
      },
      {
        "date": "2023-05",
        "demand": 327
      },
      {
        "date": "2023-06",
        "demand": 278
      },
      {
        "date": "2023-07",
        "demand": 234
      },
      {
        "date": "2023-08",
        "demand": 188
      },
      {
        "date": "2023-09",
        "demand": 199
      },
      {
        "date": "2023-10",
        "demand": 128
      },
      {
        "date": "2023-11",
        "demand": 81
      },
      {
        "date": "2023-12",
        "demand": 55
      },
      {
        "date": "2024-01",
        "demand": 52
      },
      {
        "date": "2024-02",
        "demand": 65
      },
      {
        "date": "2024-03",
        "demand": 44
      },
      {
        "date": "2024-04",
        "demand": 20
      },
      {
        "date": "2024-05",
        "demand": 20
      },
      {
        "date": "2024-06",
        "demand": 20
      },
      {
        "date": "2024-07",
        "demand": 24
      },
      {
        "date": "2024-08",
        "demand": 20
      },
      {
        "date": "2024-09",
        "demand": 36
      },
      {
        "date": "2024-10",
        "demand": 22
      },
      {
        "date": "2024-11",
        "demand": 20
      },
      {
        "date": "2024-12",
        "demand": 29
      },
      {
        "date": "2025-01",
        "demand": 32
      },
      {
        "date": "2025-02",
        "demand": 47
      },
      {
        "date": "2025-03",
        "demand": 50
      },
      {
        "date": "2025-04",
        "demand": 66
      },
      {
        "date": "2025-05",
        "demand": 43
      },
      {
        "date": "2025-06",
        "demand": 34
      },
      {
        "date": "2025-07",
        "demand": 32
      },
      {
        "date": "2025-08",
        "demand": 38
      },
      {
        "date": "2025-09",
        "demand": 54
      },
      {
        "date": "2025-10",
        "demand": 28
      },
      {
        "date": "2025-11",
        "demand": 20
      },
      {
        "date": "2025-12",
        "demand": 27
      },
      {
        "date": "2026-01",
        "demand": 24
      },
      {
        "date": "2026-02",
        "demand": 20
      },
      {
        "date": "2026-03",
        "demand": 24
      }
    ],
    "Rare Earth Magnets": [
      {
        "date": "2023-04",
        "demand": 59
      },
      {
        "date": "2023-05",
        "demand": 54
      },
      {
        "date": "2023-06",
        "demand": 53
      },
      {
        "date": "2023-07",
        "demand": 51
      },
      {
        "date": "2023-08",
        "demand": 41
      },
      {
        "date": "2023-09",
        "demand": 31
      },
      {
        "date": "2023-10",
        "demand": 20
      },
      {
        "date": "2023-11",
        "demand": 20
      },
      {
        "date": "2023-12",
        "demand": 20
      },
      {
        "date": "2024-01",
        "demand": 20
      },
      {
        "date": "2024-02",
        "demand": 20
      },
      {
        "date": "2024-03",
        "demand": 20
      },
      {
        "date": "2024-04",
        "demand": 20
      },
      {
        "date": "2024-05",
        "demand": 20
      },
      {
        "date": "2024-06",
        "demand": 20
      },
      {
        "date": "2024-07",
        "demand": 20
      },
      {
        "date": "2024-08",
        "demand": 20
      },
      {
        "date": "2024-09",
        "demand": 20
      },
      {
        "date": "2024-10",
        "demand": 20
      },
      {
        "date": "2024-11",
        "demand": 20
      },
      {
        "date": "2024-12",
        "demand": 20
      },
      {
        "date": "2025-01",
        "demand": 20
      },
      {
        "date": "2025-02",
        "demand": 20
      },
      {
        "date": "2025-03",
        "demand": 22
      },
      {
        "date": "2025-04",
        "demand": 20
      },
      {
        "date": "2025-05",
        "demand": 32
      },
      {
        "date": "2025-06",
        "demand": 22
      },
      {
        "date": "2025-07",
        "demand": 20
      },
      {
        "date": "2025-08",
        "demand": 24
      },
      {
        "date": "2025-09",
        "demand": 20
      },
      {
        "date": "2025-10",
        "demand": 20
      },
      {
        "date": "2025-11",
        "demand": 20
      },
      {
        "date": "2025-12",
        "demand": 20
      },
      {
        "date": "2026-01",
        "demand": 20
      },
      {
        "date": "2026-02",
        "demand": 20
      },
      {
        "date": "2026-03",
        "demand": 20
      }
    ]
  },
  "suppliers": [
    {
      "name": "SteelMart Inc",
      "material": "Steel Coils",
      "on_time_delivery": 86.7,
      "quality_score": 85.4,
      "price_competitiveness": 89.2,
      "responsiveness": 76.3,
      "overall_score": 85.2,
      "lead_time_days": 8,
      "min_order_qty": 100,
      "reliability": "Medium",
      "certifications": [
        "ISO 14001"
      ],
      "country": "USA",
      "years_as_vendor": 9,
      "defect_rate_pct": 2.96,
      "fill_rate_pct": 95.9
    },
    {
      "name": "MetalPro Ltd",
      "material": "Steel Coils",
      "on_time_delivery": 85.5,
      "quality_score": 94.4,
      "price_competitiveness": 83.9,
      "responsiveness": 79.7,
      "overall_score": 87.0,
      "lead_time_days": 7,
      "min_order_qty": 500,
      "reliability": "Medium",
      "certifications": [
        "ISO 9001"
      ],
      "country": "India",
      "years_as_vendor": 14,
      "defect_rate_pct": 2.19,
      "fill_rate_pct": 89.7
    },
    {
      "name": "AlloySource Co",
      "material": "Steel Coils",
      "on_time_delivery": 84.2,
      "quality_score": 79.7,
      "price_competitiveness": 79.8,
      "responsiveness": 86.1,
      "overall_score": 82.3,
      "lead_time_days": 22,
      "min_order_qty": 500,
      "reliability": "Medium",
      "certifications": [
        "ISO 14001"
      ],
      "country": "South Korea",
      "years_as_vendor": 3,
      "defect_rate_pct": 4.09,
      "fill_rate_pct": 87.2
    },
    {
      "name": "IronBridge Supply",
      "material": "Steel Coils",
      "on_time_delivery": 75.3,
      "quality_score": 91.0,
      "price_competitiveness": 88.9,
      "responsiveness": 91.0,
      "overall_score": 85.1,
      "lead_time_days": 21,
      "min_order_qty": 1000,
      "reliability": "Medium",
      "certifications": [
        "ISO 9001",
        "ISO 14001"
      ],
      "country": "Germany",
      "years_as_vendor": 12,
      "defect_rate_pct": 1.33,
      "fill_rate_pct": 99.4
    },
    {
      "name": "AluminumFirst",
      "material": "Aluminum Sheets",
      "on_time_delivery": 88.7,
      "quality_score": 78.6,
      "price_competitiveness": 73.9,
      "responsiveness": 82.7,
      "overall_score": 81.8,
      "lead_time_days": 4,
      "min_order_qty": 1000,
      "reliability": "Medium",
      "certifications": [],
      "country": "India",
      "years_as_vendor": 5,
      "defect_rate_pct": 3.88,
      "fill_rate_pct": 97.2
    },
    {
      "name": "LightMetal Corp",
      "material": "Aluminum Sheets",
      "on_time_delivery": 93.3,
      "quality_score": 98.9,
      "price_competitiveness": 80.9,
      "responsiveness": 86.5,
      "overall_score": 91.5,
      "lead_time_days": 18,
      "min_order_qty": 100,
      "reliability": "High",
      "certifications": [
        "ISO 9001",
        "Lean Certified"
      ],
      "country": "Japan",
      "years_as_vendor": 3,
      "defect_rate_pct": 0.99,
      "fill_rate_pct": 97.8
    },
    {
      "name": "AlloySource Co",
      "material": "Aluminum Sheets",
      "on_time_delivery": 85.9,
      "quality_score": 94.0,
      "price_competitiveness": 97.4,
      "responsiveness": 94.0,
      "overall_score": 91.8,
      "lead_time_days": 19,
      "min_order_qty": 200,
      "reliability": "High",
      "certifications": [
        "ISO 9001"
      ],
      "country": "India",
      "years_as_vendor": 13,
      "defect_rate_pct": 2.43,
      "fill_rate_pct": 96.7
    },
    {
      "name": "Nordic Metals",
      "material": "Aluminum Sheets",
      "on_time_delivery": 82.9,
      "quality_score": 76.3,
      "price_competitiveness": 92.9,
      "responsiveness": 97.6,
      "overall_score": 85.1,
      "lead_time_days": 26,
      "min_order_qty": 1000,
      "reliability": "Medium",
      "certifications": [
        "ISO 14001"
      ],
      "country": "USA",
      "years_as_vendor": 10,
      "defect_rate_pct": 2.66,
      "fill_rate_pct": 96.9
    },
    {
      "name": "CopperKing",
      "material": "Copper Wire",
      "on_time_delivery": 76.2,
      "quality_score": 99,
      "price_competitiveness": 83.4,
      "responsiveness": 93.6,
      "overall_score": 87.1,
      "lead_time_days": 24,
      "min_order_qty": 200,
      "reliability": "Medium",
      "certifications": [
        "ISO 9001"
      ],
      "country": "USA",
      "years_as_vendor": 14,
      "defect_rate_pct": 0.6,
      "fill_rate_pct": 89.1
    },
    {
      "name": "WireWorks Ltd",
      "material": "Copper Wire",
      "on_time_delivery": 98.3,
      "quality_score": 85.0,
      "price_competitiveness": 87.6,
      "responsiveness": 75.6,
      "overall_score": 88.8,
      "lead_time_days": 6,
      "min_order_qty": 100,
      "reliability": "High",
      "certifications": [
        "Lean Certified",
        "ISO 14001"
      ],
      "country": "India",
      "years_as_vendor": 12,
      "defect_rate_pct": 1.72,
      "fill_rate_pct": 90.7
    },
    {
      "name": "ElectraMat",
      "material": "Copper Wire",
      "on_time_delivery": 80.1,
      "quality_score": 98.2,
      "price_competitiveness": 84.5,
      "responsiveness": 97.9,
      "overall_score": 89.1,
      "lead_time_days": 14,
      "min_order_qty": 1000,
      "reliability": "High",
      "certifications": [
        "ISO 9001"
      ],
      "country": "China",
      "years_as_vendor": 7,
      "defect_rate_pct": 2.91,
      "fill_rate_pct": 87.6
    },
    {
      "name": "RedMetal GmbH",
      "material": "Copper Wire",
      "on_time_delivery": 79.9,
      "quality_score": 83.4,
      "price_competitiveness": 95.6,
      "responsiveness": 78.5,
      "overall_score": 83.9,
      "lead_time_days": 26,
      "min_order_qty": 1000,
      "reliability": "Medium",
      "certifications": [
        "ISO 14001"
      ],
      "country": "China",
      "years_as_vendor": 9,
      "defect_rate_pct": 3.46,
      "fill_rate_pct": 97.1
    },
    {
      "name": "PolyBase Inc",
      "material": "Plastic Pellets",
      "on_time_delivery": 99,
      "quality_score": 83.8,
      "price_competitiveness": 72.2,
      "responsiveness": 72.9,
      "overall_score": 85.2,
      "lead_time_days": 18,
      "min_order_qty": 100,
      "reliability": "Medium",
      "certifications": [
        "Lean Certified"
      ],
      "country": "USA",
      "years_as_vendor": 10,
      "defect_rate_pct": 2.3,
      "fill_rate_pct": 93.6
    },
    {
      "name": "PlastiCore",
      "material": "Plastic Pellets",
      "on_time_delivery": 80.5,
      "quality_score": 90.4,
      "price_competitiveness": 95.9,
      "responsiveness": 75.4,
      "overall_score": 85.8,
      "lead_time_days": 25,
      "min_order_qty": 200,
      "reliability": "Medium",
      "certifications": [
        "ISO 9001"
      ],
      "country": "South Korea",
      "years_as_vendor": 9,
      "defect_rate_pct": 4.18,
      "fill_rate_pct": 93.6
    },
    {
      "name": "ChemSupply",
      "material": "Plastic Pellets",
      "on_time_delivery": 89.2,
      "quality_score": 79.1,
      "price_competitiveness": 94.5,
      "responsiveness": 70.2,
      "overall_score": 84.4,
      "lead_time_days": 12,
      "min_order_qty": 1000,
      "reliability": "Medium",
      "certifications": [
        "ISO 14001"
      ],
      "country": "South Korea",
      "years_as_vendor": 4,
      "defect_rate_pct": 3.09,
      "fill_rate_pct": 92.9
    },
    {
      "name": "SynPoly",
      "material": "Plastic Pellets",
      "on_time_delivery": 90.0,
      "quality_score": 78.4,
      "price_competitiveness": 79.5,
      "responsiveness": 79.1,
      "overall_score": 82.8,
      "lead_time_days": 5,
      "min_order_qty": 500,
      "reliability": "Medium",
      "certifications": [
        "ISO 14001"
      ],
      "country": "USA",
      "years_as_vendor": 2,
      "defect_rate_pct": 1.14,
      "fill_rate_pct": 87.4
    },
    {
      "name": "FiberTech",
      "material": "Carbon Fiber",
      "on_time_delivery": 85.3,
      "quality_score": 81.2,
      "price_competitiveness": 75.8,
      "responsiveness": 83.2,
      "overall_score": 81.9,
      "lead_time_days": 22,
      "min_order_qty": 100,
      "reliability": "Medium",
      "certifications": [],
      "country": "Germany",
      "years_as_vendor": 10,
      "defect_rate_pct": 0.59,
      "fill_rate_pct": 88.6
    },
    {
      "name": "CompositesPro",
      "material": "Carbon Fiber",
      "on_time_delivery": 70.2,
      "quality_score": 88.7,
      "price_competitiveness": 84.8,
      "responsiveness": 73.5,
      "overall_score": 79.2,
      "lead_time_days": 27,
      "min_order_qty": 500,
      "reliability": "Medium",
      "certifications": [
        "ISO 14001"
      ],
      "country": "USA",
      "years_as_vendor": 10,
      "defect_rate_pct": 4.0,
      "fill_rate_pct": 89.8
    },
    {
      "name": "AeroMat",
      "material": "Carbon Fiber",
      "on_time_delivery": 69.8,
      "quality_score": 90.8,
      "price_competitiveness": 77.7,
      "responsiveness": 79.8,
      "overall_score": 79.2,
      "lead_time_days": 27,
      "min_order_qty": 1000,
      "reliability": "Medium",
      "certifications": [
        "ISO 9001",
        "ISO 14001"
      ],
      "country": "Japan",
      "years_as_vendor": 14,
      "defect_rate_pct": 1.07,
      "fill_rate_pct": 99.3
    },
    {
      "name": "ToraySource",
      "material": "Carbon Fiber",
      "on_time_delivery": 87.8,
      "quality_score": 92.2,
      "price_competitiveness": 86.6,
      "responsiveness": 94.7,
      "overall_score": 89.9,
      "lead_time_days": 18,
      "min_order_qty": 100,
      "reliability": "High",
      "certifications": [
        "ISO 9001"
      ],
      "country": "Japan",
      "years_as_vendor": 8,
      "defect_rate_pct": 0.9,
      "fill_rate_pct": 95.3
    },
    {
      "name": "SiliconEdge",
      "material": "Silicon Wafers",
      "on_time_delivery": 85.3,
      "quality_score": 90.5,
      "price_competitiveness": 83.9,
      "responsiveness": 69.8,
      "overall_score": 84.3,
      "lead_time_days": 24,
      "min_order_qty": 100,
      "reliability": "Medium",
      "certifications": [
        "ISO 9001"
      ],
      "country": "China",
      "years_as_vendor": 7,
      "defect_rate_pct": 1.21,
      "fill_rate_pct": 93.2
    },
    {
      "name": "WaferTech",
      "material": "Silicon Wafers",
      "on_time_delivery": 94.9,
      "quality_score": 92.1,
      "price_competitiveness": 81.6,
      "responsiveness": 76.8,
      "overall_score": 88.7,
      "lead_time_days": 6,
      "min_order_qty": 100,
      "reliability": "High",
      "certifications": [
        "ISO 9001",
        "Lean Certified"
      ],
      "country": "South Korea",
      "years_as_vendor": 15,
      "defect_rate_pct": 2.86,
      "fill_rate_pct": 89.9
    },
    {
      "name": "MicroMat",
      "material": "Silicon Wafers",
      "on_time_delivery": 73.1,
      "quality_score": 78.8,
      "price_competitiveness": 93.3,
      "responsiveness": 76.8,
      "overall_score": 79.4,
      "lead_time_days": 28,
      "min_order_qty": 1000,
      "reliability": "Medium",
      "certifications": [
        "ISO 14001"
      ],
      "country": "South Korea",
      "years_as_vendor": 13,
      "defect_rate_pct": 3.49,
      "fill_rate_pct": 89.6
    },
    {
      "name": "ChipSource Asia",
      "material": "Silicon Wafers",
      "on_time_delivery": 69.4,
      "quality_score": 83.6,
      "price_competitiveness": 94.9,
      "responsiveness": 92.1,
      "overall_score": 82.2,
      "lead_time_days": 14,
      "min_order_qty": 1000,
      "reliability": "Medium",
      "certifications": [],
      "country": "USA",
      "years_as_vendor": 13,
      "defect_rate_pct": 3.81,
      "fill_rate_pct": 87.6
    },
    {
      "name": "TitanWorks",
      "material": "Titanium Alloy",
      "on_time_delivery": 85.2,
      "quality_score": 92.5,
      "price_competitiveness": 95.9,
      "responsiveness": 93.6,
      "overall_score": 90.8,
      "lead_time_days": 11,
      "min_order_qty": 200,
      "reliability": "High",
      "certifications": [
        "ISO 9001"
      ],
      "country": "Germany",
      "years_as_vendor": 12,
      "defect_rate_pct": 1.23,
      "fill_rate_pct": 88.5
    },
    {
      "name": "AeroAlloys",
      "material": "Titanium Alloy",
      "on_time_delivery": 82.7,
      "quality_score": 96.1,
      "price_competitiveness": 81.2,
      "responsiveness": 70.5,
      "overall_score": 84.6,
      "lead_time_days": 25,
      "min_order_qty": 200,
      "reliability": "Medium",
      "certifications": [
        "ISO 9001"
      ],
      "country": "India",
      "years_as_vendor": 13,
      "defect_rate_pct": 2.11,
      "fill_rate_pct": 87.2
    },
    {
      "name": "PrecisionMetal Co",
      "material": "Titanium Alloy",
      "on_time_delivery": 86.1,
      "quality_score": 91.0,
      "price_competitiveness": 88.9,
      "responsiveness": 80.0,
      "overall_score": 87.2,
      "lead_time_days": 12,
      "min_order_qty": 1000,
      "reliability": "Medium",
      "certifications": [
        "ISO 9001"
      ],
      "country": "Germany",
      "years_as_vendor": 3,
      "defect_rate_pct": 3.98,
      "fill_rate_pct": 96.8
    },
    {
      "name": "NickelBase",
      "material": "Nickel Powder",
      "on_time_delivery": 78.6,
      "quality_score": 96.6,
      "price_competitiveness": 97.8,
      "responsiveness": 74.0,
      "overall_score": 87.1,
      "lead_time_days": 15,
      "min_order_qty": 1000,
      "reliability": "Medium",
      "certifications": [
        "ISO 9001",
        "ISO 14001"
      ],
      "country": "Japan",
      "years_as_vendor": 11,
      "defect_rate_pct": 2.29,
      "fill_rate_pct": 99.0
    },
    {
      "name": "MetalPowders Ltd",
      "material": "Nickel Powder",
      "on_time_delivery": 83.2,
      "quality_score": 80.0,
      "price_competitiveness": 75.3,
      "responsiveness": 83.7,
      "overall_score": 80.7,
      "lead_time_days": 6,
      "min_order_qty": 100,
      "reliability": "Medium",
      "certifications": [],
      "country": "Germany",
      "years_as_vendor": 9,
      "defect_rate_pct": 2.79,
      "fill_rate_pct": 96.9
    },
    {
      "name": "BatteryMat Supply",
      "material": "Nickel Powder",
      "on_time_delivery": 90.9,
      "quality_score": 77.6,
      "price_competitiveness": 87.8,
      "responsiveness": 87.9,
      "overall_score": 85.8,
      "lead_time_days": 28,
      "min_order_qty": 1000,
      "reliability": "Medium",
      "certifications": [],
      "country": "China",
      "years_as_vendor": 14,
      "defect_rate_pct": 1.14,
      "fill_rate_pct": 86.5
    },
    {
      "name": "GraphCo",
      "material": "Graphite Electrodes",
      "on_time_delivery": 97.4,
      "quality_score": 77.7,
      "price_competitiveness": 87.4,
      "responsiveness": 90.5,
      "overall_score": 88.5,
      "lead_time_days": 28,
      "min_order_qty": 500,
      "reliability": "High",
      "certifications": [
        "Lean Certified"
      ],
      "country": "China",
      "years_as_vendor": 15,
      "defect_rate_pct": 0.77,
      "fill_rate_pct": 96.1
    },
    {
      "name": "CarbonTech",
      "material": "Graphite Electrodes",
      "on_time_delivery": 74.0,
      "quality_score": 79.6,
      "price_competitiveness": 88.1,
      "responsiveness": 90.0,
      "overall_score": 80.9,
      "lead_time_days": 13,
      "min_order_qty": 500,
      "reliability": "Medium",
      "certifications": [
        "ISO 14001"
      ],
      "country": "India",
      "years_as_vendor": 14,
      "defect_rate_pct": 2.32,
      "fill_rate_pct": 87.3
    },
    {
      "name": "ElectrodeMax",
      "material": "Graphite Electrodes",
      "on_time_delivery": 68.3,
      "quality_score": 75.7,
      "price_competitiveness": 77.3,
      "responsiveness": 74.3,
      "overall_score": 73.2,
      "lead_time_days": 5,
      "min_order_qty": 200,
      "reliability": "Low",
      "certifications": [],
      "country": "China",
      "years_as_vendor": 1,
      "defect_rate_pct": 0.79,
      "fill_rate_pct": 92.5
    },
    {
      "name": "MagnetCore",
      "material": "Rare Earth Magnets",
      "on_time_delivery": 90.0,
      "quality_score": 84.6,
      "price_competitiveness": 92.5,
      "responsiveness": 94.6,
      "overall_score": 89.6,
      "lead_time_days": 22,
      "min_order_qty": 500,
      "reliability": "High",
      "certifications": [],
      "country": "South Korea",
      "years_as_vendor": 11,
      "defect_rate_pct": 3.99,
      "fill_rate_pct": 99.4
    },
    {
      "name": "REESource",
      "material": "Rare Earth Magnets",
      "on_time_delivery": 81.7,
      "quality_score": 97.1,
      "price_competitiveness": 95.7,
      "responsiveness": 80.9,
      "overall_score": 89.0,
      "lead_time_days": 6,
      "min_order_qty": 1000,
      "reliability": "High",
      "certifications": [
        "ISO 9001",
        "ISO 14001"
      ],
      "country": "India",
      "years_as_vendor": 6,
      "defect_rate_pct": 2.38,
      "fill_rate_pct": 97.4
    },
    {
      "name": "AsiaRareMetal",
      "material": "Rare Earth Magnets",
      "on_time_delivery": 87.2,
      "quality_score": 95.6,
      "price_competitiveness": 97.9,
      "responsiveness": 83.2,
      "overall_score": 91.3,
      "lead_time_days": 8,
      "min_order_qty": 200,
      "reliability": "High",
      "certifications": [
        "ISO 9001",
        "ISO 14001"
      ],
      "country": "China",
      "years_as_vendor": 11,
      "defect_rate_pct": 2.52,
      "fill_rate_pct": 85.6
    }
  ],
  "inventory": [
    {
      "material": "Steel Coils",
      "current_stock": 7901,
      "max_capacity": 8760,
      "reorder_point": 2190,
      "unit": "kg",
      "daily_usage_rate": 30.0,
      "days_of_supply": 263,
      "holding_cost_per_unit": 1.47,
      "ordering_cost": 433,
      "last_updated": "2026-04-13"
    },
    {
      "material": "Aluminum Sheets",
      "current_stock": 5255,
      "max_capacity": 10591,
      "reorder_point": 2647,
      "unit": "kg",
      "daily_usage_rate": 20.0,
      "days_of_supply": 263,
      "holding_cost_per_unit": 2.34,
      "ordering_cost": 1415,
      "last_updated": "2026-04-13"
    },
    {
      "material": "Copper Wire",
      "current_stock": 4526,
      "max_capacity": 6525,
      "reorder_point": 1631,
      "unit": "kg",
      "daily_usage_rate": 15.0,
      "days_of_supply": 302,
      "holding_cost_per_unit": 0.65,
      "ordering_cost": 965,
      "last_updated": "2026-04-13"
    },
    {
      "material": "Plastic Pellets",
      "current_stock": 1097,
      "max_capacity": 4867,
      "reorder_point": 1216,
      "unit": "kg",
      "daily_usage_rate": 40.0,
      "days_of_supply": 27,
      "holding_cost_per_unit": 2.85,
      "ordering_cost": 238,
      "last_updated": "2026-04-13"
    },
    {
      "material": "Carbon Fiber",
      "current_stock": 1161,
      "max_capacity": 9032,
      "reorder_point": 2258,
      "unit": "kg",
      "daily_usage_rate": 6.0,
      "days_of_supply": 194,
      "holding_cost_per_unit": 2.42,
      "ordering_cost": 244,
      "last_updated": "2026-04-13"
    },
    {
      "material": "Silicon Wafers",
      "current_stock": 7334,
      "max_capacity": 11795,
      "reorder_point": 2948,
      "unit": "kg",
      "daily_usage_rate": 10.7,
      "days_of_supply": 685,
      "holding_cost_per_unit": 2.9,
      "ordering_cost": 337,
      "last_updated": "2026-04-13"
    },
    {
      "material": "Titanium Alloy",
      "current_stock": 3195,
      "max_capacity": 7400,
      "reorder_point": 1850,
      "unit": "kg",
      "daily_usage_rate": 3.0,
      "days_of_supply": 1065,
      "holding_cost_per_unit": 2.57,
      "ordering_cost": 442,
      "last_updated": "2026-04-13"
    },
    {
      "material": "Nickel Powder",
      "current_stock": 3209,
      "max_capacity": 6936,
      "reorder_point": 1734,
      "unit": "kg",
      "daily_usage_rate": 8.0,
      "days_of_supply": 401,
      "holding_cost_per_unit": 3.15,
      "ordering_cost": 392,
      "last_updated": "2026-04-13"
    },
    {
      "material": "Graphite Electrodes",
      "current_stock": 2544,
      "max_capacity": 5337,
      "reorder_point": 1334,
      "unit": "kg",
      "daily_usage_rate": 12.0,
      "days_of_supply": 212,
      "holding_cost_per_unit": 2.13,
      "ordering_cost": 1095,
      "last_updated": "2026-04-13"
    },
    {
      "material": "Rare Earth Magnets",
      "current_stock": 6114,
      "max_capacity": 11400,
      "reorder_point": 2850,
      "unit": "kg",
      "daily_usage_rate": 2.0,
      "days_of_supply": 3057,
      "holding_cost_per_unit": 0.8,
      "ordering_cost": 446,
      "last_updated": "2026-04-13"
    }
  ],
  "shock_events": {
    "3": "Supply chain disruption",
    "7": "Global demand surge",
    "12": "Trade tariff introduced",
    "17": "Port strike resolved",
    "22": "Energy price spike",
    "27": "New supply source opened",
    "31": "Geopolitical tension",
    "35": "Market correction"
  }
}